{
  "updated_at": "2026-04-15 14:58",
  "indices": {
    "sh000001": {
      "name": "上证指数",
      "price": "4039.47",
      "pct": "+0.32",
      "high": "4050.62",
      "low": "4020.90"
    },
    "sz399001": {
      "name": "深证成指",
      "price": "14736.01",
      "pct": "+0.66",
      "high": "14738.53",
      "low": "14440.21"
    },
    "sz399006": {
      "name": "创业板指",
      "price": "3596.08",
      "pct": "+1.06",
      "high": "3599.98",
      "low": "3491.45"
    },
    "sh000300": {
      "name": "沪深300",
      "price": "4726.64",
      "pct": "+0.54",
      "high": "4731.27",
      "low": "4672.56"
    }
  },
  "limit_up": [
    {
      "symbol": "sh688287",
      "code": "688287",
      "name": "*ST观典",
      "trade": "1.960",
      "pricechange": 0.33,
      "changepercent": 20.245,
      "buy": "1.960",
      "sell": "1.960",
      "settlement": "1.630",
      "open": "1.820",
      "high": "1.960",
      "low": "1.770",
      "volume": 25042667,
      "amount": 47523910,
      "ticktime": "14:57:57",
      "per": -5.297,
      "pb": 0.947,
      "mktcap": 72621.0576,
      "nmc": 72621.0576,
      "turnoverratio": 6.75887
    },
    {
      "symbol": "sh688805",
      "code": "688805",
      "name": "健信超导",
      "trade": "56.920",
      "pricechange": 9.49,
      "changepercent": 20.008,
      "buy": "56.920",
      "sell": "56.920",
      "settlement": "47.430",
      "open": "49.090",
      "high": "56.920",
      "low": "49.090",
      "volume": 9416408,
      "amount": 517310729,
      "ticktime": "14:58:02",
      "per": 129.364,
      "pb": 18.925,
      "mktcap": 954434.56,
      "nmc": 179405.345428,
      "turnoverratio": 29.87547
    },
    {
      "symbol": "sz301189",
      "code": "301189",
      "name": "奥尼电子",
      "trade": "86.390",
      "pricechange": 14.4,
      "changepercent": 20.003,
      "buy": "86.390",
      "sell": "86.390",
      "settlement": "71.990",
      "open": "84.590",
      "high": "86.390",
      "low": "83.000",
      "volume": 13271107,
      "amount": 1136196061,
      "ticktime": "14:57:54",
      "per": -115.187,
      "pb": 4.784,
      "mktcap": 1005549.061135,
      "nmc": 965476.264847,
      "turnoverratio": 11.87487
    },
    {
      "symbol": "sh688166",
      "code": "688166",
      "name": "博瑞医药",
      "trade": "57.660",
      "pricechange": 9.61,
      "changepercent": 20,
      "buy": "57.660",
      "sell": "57.660",
      "settlement": "48.050",
      "open": "48.600",
      "high": "57.660",
      "low": "47.310",
      "volume": 28442547,
      "amount": 1523406242,
      "ticktime": "14:58:01",
      "per": 443.538,
      "pb": 9.917,
      "mktcap": 2439620.281764,
      "nmc": 2439620.281764,
      "turnoverratio": 6.72235
    },
    {
      "symbol": "sz301408",
      "code": "301408",
      "name": "华人健康",
      "trade": "20.780",
      "pricechange": 3.46,
      "changepercent": 19.977,
      "buy": "20.780",
      "sell": "20.780",
      "settlement": "17.320",
      "open": "17.630",
      "high": "20.780",
      "low": "17.630",
      "volume": 65031646,
      "amount": 1271207300,
      "ticktime": "14:57:54",
      "per": 61.118,
      "pb": 3.966,
      "mktcap": 831220.78,
      "nmc": 475777.639434,
      "turnoverratio": 28.40313
    },
    {
      "symbol": "sz300097",
      "code": "300097",
      "name": "智云股份",
      "trade": "9.840",
      "pricechange": 1.47,
      "changepercent": 17.563,
      "buy": "9.820",
      "sell": "9.820",
      "settlement": "8.370",
      "open": "8.360",
      "high": "10.040",
      "low": "8.330",
      "volume": 55511360,
      "amount": 525825307,
      "ticktime": "14:57:54",
      "per": -10.358,
      "pb": 13.217,
      "mktcap": 283932.874296,
      "nmc": 265688.312832,
      "turnoverratio": 20.55912
    },
    {
      "symbol": "sz301017",
      "code": "301017",
      "name": "漱玉平民",
      "trade": "16.280",
      "pricechange": 2.22,
      "changepercent": 15.789,
      "buy": "16.260",
      "sell": "16.260",
      "settlement": "14.060",
      "open": "14.300",
      "high": "16.780",
      "low": "14.260",
      "volume": 37098661,
      "amount": 571129474,
      "ticktime": "14:57:54",
      "per": -34.638,
      "pb": 3.326,
      "mktcap": 660327.311996,
      "nmc": 421154.535296,
      "turnoverratio": 14.34073
    },
    {
      "symbol": "sz301248",
      "code": "301248",
      "name": "杰创智能",
      "trade": "57.680",
      "pricechange": 7.25,
      "changepercent": 14.376,
      "buy": "57.670",
      "sell": "57.670",
      "settlement": "50.430",
      "open": "51.010",
      "high": "58.000",
      "low": "50.350",
      "volume": 16305896,
      "amount": 897834493,
      "ticktime": "14:57:54",
      "per": -110.923,
      "pb": 5.804,
      "mktcap": 886570.44,
      "nmc": 647911.9416,
      "turnoverratio": 14.51623
    },
    {
      "symbol": "sh688253",
      "code": "688253",
      "name": "英诺特",
      "trade": "43.090",
      "pricechange": 5.32,
      "changepercent": 14.085,
      "buy": "43.100",
      "sell": "43.100",
      "settlement": "37.770",
      "open": "38.530",
      "high": "43.590",
      "low": "38.520",
      "volume": 6161541,
      "amount": 258346168,
      "ticktime": "14:58:03",
      "per": 23.807,
      "pb": 2.905,
      "mktcap": 590265.417644,
      "nmc": 590265.417644,
      "turnoverratio": 4.49799
    },
    {
      "symbol": "sz300051",
      "code": "300051",
      "name": "琏升科技",
      "trade": "16.070",
      "pricechange": 1.9,
      "changepercent": 13.409,
      "buy": "16.070",
      "sell": "16.070",
      "settlement": "14.170",
      "open": "13.970",
      "high": "16.500",
      "low": "13.970",
      "volume": 63155845,
      "amount": 987263521,
      "ticktime": "14:57:54",
      "per": -53.567,
      "pb": 37.062,
      "mktcap": 597832.42783,
      "nmc": 590855.356105,
      "turnoverratio": 17.17704
    },
    {
      "symbol": "sh688603",
      "code": "688603",
      "name": "天承科技",
      "trade": "98.490",
      "pricechange": 11.36,
      "changepercent": 13.038,
      "buy": "98.000",
      "sell": "98.000",
      "settlement": "87.130",
      "open": "87.970",
      "high": "100.800",
      "low": "86.930",
      "volume": 10427788,
      "amount": 1002046109,
      "ticktime": "14:58:01",
      "per": 110.663,
      "pb": 10.537,
      "mktcap": 1228411.836876,
      "nmc": 467055.407343,
      "turnoverratio": 21.98953
    },
    {
      "symbol": "sz300857",
      "code": "300857",
      "name": "协创数据",
      "trade": "280.690",
      "pricechange": 31.09,
      "changepercent": 12.456,
      "buy": "280.690",
      "sell": "280.690",
      "settlement": "249.600",
      "open": "280.190",
      "high": "288.680",
      "low": "268.980",
      "volume": 40356100,
      "amount": 11110728688,
      "ticktime": "14:57:54",
      "per": 83.044,
      "pb": 22.126,
      "mktcap": 9715263.865061,
      "nmc": 9665079.664858,
      "turnoverratio": 11.72008
    },
    {
      "symbol": "sz301631",
      "code": "301631",
      "name": "壹连科技",
      "trade": "102.960",
      "pricechange": 11.16,
      "changepercent": 12.157,
      "buy": "102.980",
      "sell": "102.980",
      "settlement": "91.800",
      "open": "93.600",
      "high": "108.000",
      "low": "91.870",
      "volume": 5590745,
      "amount": 558658559,
      "ticktime": "14:57:54",
      "per": 22.238,
      "pb": 3.765,
      "mktcap": 941204.51568,
      "nmc": 316143.807408,
      "turnoverratio": 18.20763
    },
    {
      "symbol": "sh688618",
      "code": "688618",
      "name": "三旺通信",
      "trade": "39.150",
      "pricechange": 4.19,
      "changepercent": 11.985,
      "buy": "39.400",
      "sell": "39.400",
      "settlement": "34.960",
      "open": "35.100",
      "high": "41.950",
      "low": "35.100",
      "volume": 11316594,
      "amount": 443788375,
      "ticktime": "14:58:00",
      "per": 130.5,
      "pb": 4.916,
      "mktcap": 431376.74145,
      "nmc": 430837.32492,
      "turnoverratio": 10.28334
    },
    {
      "symbol": "sz300444",
      "code": "300444",
      "name": "双杰电气",
      "trade": "15.370",
      "pricechange": 1.52,
      "changepercent": 10.975,
      "buy": "15.370",
      "sell": "15.370",
      "settlement": "13.850",
      "open": "14.070",
      "high": "15.540",
      "low": "13.890",
      "volume": 134368318,
      "amount": 2010245269,
      "ticktime": "14:57:54",
      "per": 66.193,
      "pb": 6.756,
      "mktcap": 1227486.76333,
      "nmc": 955163.576363,
      "turnoverratio": 21.62186
    },
    {
      "symbol": "sz301232",
      "code": "301232",
      "name": "飞沃科技",
      "trade": "216.120",
      "pricechange": 21.08,
      "changepercent": 10.808,
      "buy": "216.000",
      "sell": "216.000",
      "settlement": "195.040",
      "open": "196.660",
      "high": "228.000",
      "low": "196.000",
      "volume": 11589723,
      "amount": 2504266113,
      "ticktime": "14:57:54",
      "per": 432.24,
      "pb": 11.528,
      "mktcap": 1624408.643364,
      "nmc": 965348.93118,
      "turnoverratio": 25.94679
    },
    {
      "symbol": "sz300798",
      "code": "300798",
      "name": "锦鸡股份",
      "trade": "11.100",
      "pricechange": 1.08,
      "changepercent": 10.778,
      "buy": "11.090",
      "sell": "11.090",
      "settlement": "10.020",
      "open": "10.120",
      "high": "11.580",
      "low": "9.690",
      "volume": 74511055,
      "amount": 794610758,
      "ticktime": "14:57:54",
      "per": 917.355,
      "pb": 3.098,
      "mktcap": 520440.23103,
      "nmc": 423372.2817,
      "turnoverratio": 19.53535
    },
    {
      "symbol": "sh688802",
      "code": "688802",
      "name": "沐曦股份",
      "trade": "680.000",
      "pricechange": 66.1,
      "changepercent": 10.767,
      "buy": "679.900",
      "sell": "679.900",
      "settlement": "613.900",
      "open": "615.010",
      "high": "707.770",
      "low": "610.010",
      "volume": 4614657,
      "amount": 3053809435,
      "ticktime": "14:58:03",
      "per": -278.689,
      "pb": 20.665,
      "mktcap": 27206800,
      "nmc": 1233450.164,
      "turnoverratio": 25.44056
    },
    {
      "symbol": "sz301396",
      "code": "301396",
      "name": "宏景科技",
      "trade": "246.100",
      "pricechange": 23.42,
      "changepercent": 10.517,
      "buy": "246.200",
      "sell": "246.200",
      "settlement": "222.680",
      "open": "222.000",
      "high": "252.880",
      "low": "222.000",
      "volume": 16212006,
      "amount": 3869024811,
      "ticktime": "14:57:54",
      "per": -356.667,
      "pb": 29.309,
      "mktcap": 3778066.83167,
      "nmc": 1872355.23114,
      "turnoverratio": 21.30886
    },
    {
      "symbol": "sz301055",
      "code": "301055",
      "name": "张小泉",
      "trade": "33.020",
      "pricechange": 3.08,
      "changepercent": 10.287,
      "buy": "32.800",
      "sell": "32.800",
      "settlement": "29.940",
      "open": "30.380",
      "high": "33.100",
      "low": "29.500",
      "volume": 11641694,
      "amount": 370535088,
      "ticktime": "14:57:54",
      "per": 206.375,
      "pb": 7.871,
      "mktcap": 515112,
      "nmc": 515112,
      "turnoverratio": 7.46262
    },
    {
      "symbol": "sz000785",
      "code": "000785",
      "name": "居然智家",
      "trade": "2.700",
      "pricechange": 0.25,
      "changepercent": 10.204,
      "buy": "2.700",
      "sell": "2.700",
      "settlement": "2.450",
      "open": "2.460",
      "high": "2.700",
      "low": "2.460",
      "volume": 131073743,
      "amount": 348131112,
      "ticktime": "14:58:03",
      "per": 22.5,
      "pb": 0.816,
      "mktcap": 1681303.17978,
      "nmc": 1592350.23528,
      "turnoverratio": 2.2225
    },
    {
      "symbol": "sz002124",
      "code": "002124",
      "name": "天邦食品",
      "trade": "3.140",
      "pricechange": 0.29,
      "changepercent": 10.175,
      "buy": "3.140",
      "sell": "3.140",
      "settlement": "2.850",
      "open": "2.990",
      "high": "3.140",
      "low": "2.900",
      "volume": 388828791,
      "amount": 1209503954,
      "ticktime": "14:58:03",
      "per": 4.758,
      "pb": 1.773,
      "mktcap": 697687.223248,
      "nmc": 619319.359472,
      "turnoverratio": 19.71394
    },
    {
      "symbol": "sz002589",
      "code": "002589",
      "name": "瑞康医药",
      "trade": "3.590",
      "pricechange": 0.33,
      "changepercent": 10.123,
      "buy": "3.590",
      "sell": "3.590",
      "settlement": "3.260",
      "open": "3.320",
      "high": "3.590",
      "low": "3.310",
      "volume": 93750304,
      "amount": 330822950,
      "ticktime": "14:58:03",
      "per": 262.044,
      "pb": 1.01,
      "mktcap": 540191.059089,
      "nmc": 490247.365732,
      "turnoverratio": 6.86518
    },
    {
      "symbol": "sh600572",
      "code": "600572",
      "name": "康恩贝",
      "trade": "4.800",
      "pricechange": 0.44,
      "changepercent": 10.092,
      "buy": "4.800",
      "sell": "4.800",
      "settlement": "4.360",
      "open": "4.370",
      "high": "4.800",
      "low": "4.350",
      "volume": 207199372,
      "amount": 964927447,
      "ticktime": "14:58:01",
      "per": 19.2,
      "pb": 1.724,
      "mktcap": 1217709.66768,
      "nmc": 1214473.57824,
      "turnoverratio": 8.1892
    },
    {
      "symbol": "sz000788",
      "code": "000788",
      "name": "北大医药",
      "trade": "6.770",
      "pricechange": 0.62,
      "changepercent": 10.081,
      "buy": "6.770",
      "sell": "6.770",
      "settlement": "6.150",
      "open": "6.210",
      "high": "6.770",
      "low": "6.090",
      "volume": 115474111,
      "amount": 740931217,
      "ticktime": "14:58:03",
      "per": 29.244,
      "pb": 2.498,
      "mktcap": 403483.486725,
      "nmc": 403483.486725,
      "turnoverratio": 19.37526
    },
    {
      "symbol": "sz002798",
      "code": "002798",
      "name": "帝欧水华",
      "trade": "6.670",
      "pricechange": 0.61,
      "changepercent": 10.066,
      "buy": "0.000",
      "sell": "0.000",
      "settlement": "6.060",
      "open": "6.100",
      "high": "6.670",
      "low": "6.070",
      "volume": 20199947,
      "amount": 131907865,
      "ticktime": "14:57:00",
      "per": -4.276,
      "pb": 1.932,
      "mktcap": 366968.450529,
      "nmc": 319774.50735,
      "turnoverratio": 4.2134
    },
    {
      "symbol": "sh605388",
      "code": "605388",
      "name": "均瑶健康",
      "trade": "7.330",
      "pricechange": 0.67,
      "changepercent": 10.06,
      "buy": "7.330",
      "sell": "7.330",
      "settlement": "6.660",
      "open": "6.600",
      "high": "7.330",
      "low": "6.500",
      "volume": 39460434,
      "amount": 277643834,
      "ticktime": "14:58:03",
      "per": -146.6,
      "pb": 2.566,
      "mktcap": 440154.772,
      "nmc": 440154.772,
      "turnoverratio": 6.57144
    },
    {
      "symbol": "sh600267",
      "code": "600267",
      "name": "海正药业",
      "trade": "11.390",
      "pricechange": 1.04,
      "changepercent": 10.048,
      "buy": "11.390",
      "sell": "11.390",
      "settlement": "10.350",
      "open": "10.400",
      "high": "11.390",
      "low": "10.400",
      "volume": 49174920,
      "amount": 546634415,
      "ticktime": "14:57:59",
      "per": 24.761,
      "pb": 1.586,
      "mktcap": 1365389.002244,
      "nmc": 1365389.002244,
      "turnoverratio": 4.10214
    },
    {
      "symbol": "sh603815",
      "code": "603815",
      "name": "交建股份",
      "trade": "6.360",
      "pricechange": 0.58,
      "changepercent": 10.035,
      "buy": "6.360",
      "sell": "6.360",
      "settlement": "5.780",
      "open": "5.820",
      "high": "6.360",
      "low": "5.820",
      "volume": 21729500,
      "amount": 135374580,
      "ticktime": "14:58:00",
      "per": 30.286,
      "pb": 1.628,
      "mktcap": 393635.81346,
      "nmc": 393635.81346,
      "turnoverratio": 3.51085
    },
    {
      "symbol": "sz002361",
      "code": "002361",
      "name": "神剑股份",
      "trade": "18.540",
      "pricechange": 1.69,
      "changepercent": 10.03,
      "buy": "18.540",
      "sell": "18.540",
      "settlement": "16.850",
      "open": "16.850",
      "high": "18.540",
      "low": "16.600",
      "volume": 308410319,
      "amount": 5453627660,
      "ticktime": "14:58:03",
      "per": 523.729,
      "pb": 7.966,
      "mktcap": 1763218.832526,
      "nmc": 1500114.012336,
      "turnoverratio": 38.11662
    },
    {
      "symbol": "sz001896",
      "code": "001896",
      "name": "豫能控股",
      "trade": "16.570",
      "pricechange": 1.51,
      "changepercent": 10.027,
      "buy": "16.570",
      "sell": "16.570",
      "settlement": "15.060",
      "open": "15.060",
      "high": "16.570",
      "low": "14.200",
      "volume": 266051499,
      "amount": 4217022127,
      "ticktime": "14:58:03",
      "per": 64.777,
      "pb": 7.205,
      "mktcap": 2528219.66381,
      "nmc": 2528219.66381,
      "turnoverratio": 17.43707
    },
    {
      "symbol": "sz001208",
      "code": "001208",
      "name": "华菱线缆",
      "trade": "21.400",
      "pricechange": 1.95,
      "changepercent": 10.026,
      "buy": "21.400",
      "sell": "21.400",
      "settlement": "19.450",
      "open": "19.600",
      "high": "21.400",
      "low": "19.500",
      "volume": 44478936,
      "amount": 924944709,
      "ticktime": "14:58:03",
      "per": 107,
      "pb": 4.681,
      "mktcap": 1366069.92448,
      "nmc": 563269.92858,
      "turnoverratio": 16.89863
    },
    {
      "symbol": "sz002787",
      "code": "002787",
      "name": "华源控股",
      "trade": "16.680",
      "pricechange": 1.52,
      "changepercent": 10.026,
      "buy": "16.680",
      "sell": "16.680",
      "settlement": "15.160",
      "open": "15.180",
      "high": "16.680",
      "low": "15.180",
      "volume": 27764052,
      "amount": 455014628,
      "ticktime": "14:58:03",
      "per": 49.059,
      "pb": 3.024,
      "mktcap": 559074.567132,
      "nmc": 418434.670152,
      "turnoverratio": 11.06754
    },
    {
      "symbol": "sz002705",
      "code": "002705",
      "name": "新宝股份",
      "trade": "17.340",
      "pricechange": 1.58,
      "changepercent": 10.025,
      "buy": "17.340",
      "sell": "17.340",
      "settlement": "15.760",
      "open": "16.110",
      "high": "17.340",
      "low": "15.710",
      "volume": 49627214,
      "amount": 832778971,
      "ticktime": "14:58:03",
      "per": 13.439,
      "pb": 1.659,
      "mktcap": 1407792.60252,
      "nmc": 1401251.2956,
      "turnoverratio": 6.1412
    },
    {
      "symbol": "sh603327",
      "code": "603327",
      "name": "福蓉科技",
      "trade": "10.540",
      "pricechange": 0.96,
      "changepercent": 10.021,
      "buy": "10.540",
      "sell": "10.540",
      "settlement": "9.580",
      "open": "9.610",
      "high": "10.540",
      "low": "9.610",
      "volume": 48120674,
      "amount": 499406524,
      "ticktime": "14:58:00",
      "per": 49.345,
      "pb": 5.509,
      "mktcap": 1101914.16544,
      "nmc": 1101914.16544,
      "turnoverratio": 4.60283
    },
    {
      "symbol": "sh605222",
      "code": "605222",
      "name": "起帆电缆",
      "trade": "25.800",
      "pricechange": 2.35,
      "changepercent": 10.021,
      "buy": "25.800",
      "sell": "25.800",
      "settlement": "23.450",
      "open": "23.480",
      "high": "25.800",
      "low": "23.300",
      "volume": 23451385,
      "amount": 584390646,
      "ticktime": "14:58:00",
      "per": 80.625,
      "pb": 2.284,
      "mktcap": 1065290.58366,
      "nmc": 1065290.58366,
      "turnoverratio": 5.67963
    },
    {
      "symbol": "sh600135",
      "code": "600135",
      "name": "乐凯胶片",
      "trade": "11.200",
      "pricechange": 1.02,
      "changepercent": 10.02,
      "buy": "11.200",
      "sell": "11.200",
      "settlement": "10.180",
      "open": "10.180",
      "high": "11.200",
      "low": "10.120",
      "volume": 24944567,
      "amount": 271824591,
      "ticktime": "14:58:00",
      "per": -62.78,
      "pb": 2.605,
      "mktcap": 619703.95088,
      "nmc": 619703.95088,
      "turnoverratio": 4.50827
    },
    {
      "symbol": "sh603216",
      "code": "603216",
      "name": "梦天家居",
      "trade": "33.170",
      "pricechange": 3.02,
      "changepercent": 10.017,
      "buy": "33.170",
      "sell": "33.170",
      "settlement": "30.150",
      "open": "30.260",
      "high": "33.170",
      "low": "29.900",
      "volume": 8857895,
      "amount": 282836508,
      "ticktime": "14:57:42",
      "per": 118.464,
      "pb": 4.123,
      "mktcap": 738662.73,
      "nmc": 738662.73,
      "turnoverratio": 3.97768
    },
    {
      "symbol": "sz002580",
      "code": "002580",
      "name": "圣阳股份",
      "trade": "25.270",
      "pricechange": 2.3,
      "changepercent": 10.013,
      "buy": "25.270",
      "sell": "25.270",
      "settlement": "22.970",
      "open": "24.480",
      "high": "25.270",
      "low": "24.480",
      "volume": 107822358,
      "amount": 2706058078,
      "ticktime": "14:58:03",
      "per": 56.156,
      "pb": 4.929,
      "mktcap": 1146926.945311,
      "nmc": 1143060.1476,
      "turnoverratio": 23.83664
    },
    {
      "symbol": "sh603063",
      "code": "603063",
      "name": "禾望电气",
      "trade": "38.030",
      "pricechange": 3.46,
      "changepercent": 10.009,
      "buy": "38.030",
      "sell": "38.030",
      "settlement": "34.570",
      "open": "35.610",
      "high": "38.030",
      "low": "35.610",
      "volume": 66393253,
      "amount": 2499880187,
      "ticktime": "14:58:00",
      "per": 32.504,
      "pb": 3.343,
      "mktcap": 1744820.172576,
      "nmc": 1744820.172576,
      "turnoverratio": 14.47104
    },
    {
      "symbol": "sh603538",
      "code": "603538",
      "name": "美诺华",
      "trade": "56.060",
      "pricechange": 5.1,
      "changepercent": 10.008,
      "buy": "56.060",
      "sell": "56.060",
      "settlement": "50.960",
      "open": "50.910",
      "high": "56.060",
      "low": "50.180",
      "volume": 69252357,
      "amount": 3714541916,
      "ticktime": "14:58:02",
      "per": 180.839,
      "pb": 5.5,
      "mktcap": 1236054.875888,
      "nmc": 1212205.382208,
      "turnoverratio": 32.02664
    },
    {
      "symbol": "sh605366",
      "code": "605366",
      "name": "宏柏新材",
      "trade": "13.410",
      "pricechange": 1.22,
      "changepercent": 10.008,
      "buy": "13.410",
      "sell": "13.410",
      "settlement": "12.190",
      "open": "12.200",
      "high": "13.410",
      "low": "12.080",
      "volume": 41570215,
      "amount": 536339950,
      "ticktime": "14:57:58",
      "per": -268.2,
      "pb": 5.147,
      "mktcap": 1040720.1957,
      "nmc": 1040720.1957,
      "turnoverratio": 5.35645
    },
    {
      "symbol": "sz002297",
      "code": "002297",
      "name": "博云新材",
      "trade": "14.620",
      "pricechange": 1.33,
      "changepercent": 10.008,
      "buy": "14.620",
      "sell": "14.620",
      "settlement": "13.290",
      "open": "14.620",
      "high": "14.620",
      "low": "14.620",
      "volume": 9722451,
      "amount": 142142234,
      "ticktime": "14:58:03",
      "per": 135.496,
      "pb": 3.939,
      "mktcap": 837879.245378,
      "nmc": 837879.245378,
      "turnoverratio": 1.69645
    },
    {
      "symbol": "sh603629",
      "code": "603629",
      "name": "利通电子",
      "trade": "87.950",
      "pricechange": 8,
      "changepercent": 10.006,
      "buy": "87.950",
      "sell": "87.950",
      "settlement": "79.950",
      "open": "81.550",
      "high": "87.950",
      "low": "79.950",
      "volume": 44171595,
      "amount": 3709929756,
      "ticktime": "14:58:01",
      "per": 879.5,
      "pb": 12.35,
      "mktcap": 2307104.4,
      "nmc": 2259013.34,
      "turnoverratio": 17.19729
    },
    {
      "symbol": "sz002990",
      "code": "002990",
      "name": "盛视科技",
      "trade": "42.110",
      "pricechange": 3.83,
      "changepercent": 10.005,
      "buy": "42.110",
      "sell": "42.110",
      "settlement": "38.280",
      "open": "37.960",
      "high": "42.110",
      "low": "37.380",
      "volume": 29684894,
      "amount": 1185243848,
      "ticktime": "14:57:54",
      "per": 127.606,
      "pb": 4.429,
      "mktcap": 1102659.353118,
      "nmc": 571847.959343,
      "turnoverratio": 21.8595
    },
    {
      "symbol": "sh605098",
      "code": "605098",
      "name": "行动教育",
      "trade": "60.150",
      "pricechange": 5.47,
      "changepercent": 10.004,
      "buy": "60.150",
      "sell": "60.150",
      "settlement": "54.680",
      "open": "58.000",
      "high": "60.150",
      "low": "57.670",
      "volume": 2166433,
      "amount": 129182121,
      "ticktime": "14:58:01",
      "per": 22.444,
      "pb": 7.099,
      "mktcap": 717295.3665,
      "nmc": 717295.3665,
      "turnoverratio": 1.8167
    },
    {
      "symbol": "sh600605",
      "code": "600605",
      "name": "汇通能源",
      "trade": "32.330",
      "pricechange": 2.94,
      "changepercent": 10.003,
      "buy": "32.330",
      "sell": "32.330",
      "settlement": "29.390",
      "open": "31.300",
      "high": "32.330",
      "low": "30.120",
      "volume": 18823232,
      "amount": 595844449,
      "ticktime": "14:58:00",
      "per": 269.417,
      "pb": 4.698,
      "mktcap": 666911.092957,
      "nmc": 666911.092957,
      "turnoverratio": 9.12498
    },
    {
      "symbol": "sh603459",
      "code": "603459",
      "name": "红板科技",
      "trade": "68.400",
      "pricechange": 6.22,
      "changepercent": 10.003,
      "buy": "68.400",
      "sell": "68.400",
      "settlement": "62.180",
      "open": "60.360",
      "high": "68.400",
      "low": "60.330",
      "volume": 25639301,
      "amount": 1709748023,
      "ticktime": "14:58:02",
      "per": 82.41,
      "pb": 19.268,
      "mktcap": 5155674.54192,
      "nmc": 540714.70872,
      "turnoverratio": 32.43352
    },
    {
      "symbol": "sh603444",
      "code": "603444",
      "name": "吉比特",
      "trade": "393.340",
      "pricechange": 35.76,
      "changepercent": 10.001,
      "buy": "393.340",
      "sell": "393.340",
      "settlement": "357.580",
      "open": "369.990",
      "high": "393.340",
      "low": "369.990",
      "volume": 3709885,
      "amount": 1441315891,
      "ticktime": "14:58:01",
      "per": 15.797,
      "pb": 5.142,
      "mktcap": 2833664.666734,
      "nmc": 2833664.666734,
      "turnoverratio": 5.14968
    },
    {
      "symbol": "sh603150",
      "code": "603150",
      "name": "万朗磁塑",
      "trade": "57.530",
      "pricechange": 5.23,
      "changepercent": 10,
      "buy": "57.530",
      "sell": "0.000",
      "settlement": "52.300",
      "open": "53.870",
      "high": "57.530",
      "low": "52.310",
      "volume": 3484700,
      "amount": 193989382,
      "ticktime": "14:57:47",
      "per": 34.449,
      "pb": 2.903,
      "mktcap": 491783.699,
      "nmc": 491783.699,
      "turnoverratio": 4.07648
    },
    {
      "symbol": "sh603285",
      "code": "603285",
      "name": "键邦股份",
      "trade": "34.650",
      "pricechange": 3.15,
      "changepercent": 10,
      "buy": "34.650",
      "sell": "34.650",
      "settlement": "31.500",
      "open": "31.990",
      "high": "34.650",
      "low": "31.560",
      "volume": 7190006,
      "amount": 245834493,
      "ticktime": "14:58:00",
      "per": 30.13,
      "pb": 3.307,
      "mktcap": 554400,
      "nmc": 215858.3427,
      "turnoverratio": 11.54154
    },
    {
      "symbol": "sh603687",
      "code": "603687",
      "name": "大胜达",
      "trade": "18.040",
      "pricechange": 1.64,
      "changepercent": 10,
      "buy": "18.040",
      "sell": "18.040",
      "settlement": "16.400",
      "open": "18.040",
      "high": "18.040",
      "low": "18.040",
      "volume": 20991000,
      "amount": 378677640,
      "ticktime": "14:58:00",
      "per": 94.947,
      "pb": 3.045,
      "mktcap": 992257.482656,
      "nmc": 992257.482656,
      "turnoverratio": 3.81632
    },
    {
      "symbol": "sh603950",
      "code": "603950",
      "name": "长源东谷",
      "trade": "59.840",
      "pricechange": 5.44,
      "changepercent": 10,
      "buy": "59.840",
      "sell": "59.840",
      "settlement": "54.400",
      "open": "57.660",
      "high": "59.840",
      "low": "56.910",
      "volume": 10380104,
      "amount": 615164830,
      "ticktime": "14:58:01",
      "per": 49.867,
      "pb": 6.439,
      "mktcap": 1939598.7072,
      "nmc": 1936463.0912,
      "turnoverratio": 3.20763
    },
    {
      "symbol": "sh605289",
      "code": "605289",
      "name": "罗曼股份",
      "trade": "126.610",
      "pricechange": 11.51,
      "changepercent": 10,
      "buy": "126.610",
      "sell": "126.610",
      "settlement": "115.100",
      "open": "115.000",
      "high": "126.610",
      "low": "115.000",
      "volume": 5668150,
      "amount": 697085656,
      "ticktime": "14:58:01",
      "per": 253.22,
      "pb": 10.486,
      "mktcap": 1380143.9575,
      "nmc": 1371661.0875,
      "turnoverratio": 5.23194
    },
    {
      "symbol": "sz000026",
      "code": "000026",
      "name": "飞亚达",
      "trade": "17.820",
      "pricechange": 1.62,
      "changepercent": 10,
      "buy": "17.820",
      "sell": "17.820",
      "settlement": "16.200",
      "open": "16.120",
      "high": "17.820",
      "low": "15.910",
      "volume": 36549869,
      "amount": 626276031,
      "ticktime": "14:58:03",
      "per": 82.768,
      "pb": 2.167,
      "mktcap": 723071.460474,
      "nmc": 649647.226206,
      "turnoverratio": 10.02573
    },
    {
      "symbol": "sz002468",
      "code": "002468",
      "name": "申通快递",
      "trade": "16.390",
      "pricechange": 1.49,
      "changepercent": 10,
      "buy": "16.390",
      "sell": "16.390",
      "settlement": "14.900",
      "open": "16.390",
      "high": "16.390",
      "low": "16.390",
      "volume": 9651556,
      "amount": 158189003,
      "ticktime": "14:57:54",
      "per": 23.754,
      "pb": 2.439,
      "mktcap": 2508984.750074,
      "nmc": 2404740.744274,
      "turnoverratio": 0.65782
    },
    {
      "symbol": "sz002788",
      "code": "002788",
      "name": "鹭燕医药",
      "trade": "15.950",
      "pricechange": 1.45,
      "changepercent": 10,
      "buy": "15.950",
      "sell": "15.950",
      "settlement": "14.500",
      "open": "14.620",
      "high": "15.950",
      "low": "14.620",
      "volume": 71404028,
      "amount": 1090954469,
      "ticktime": "14:58:03",
      "per": 17.921,
      "pb": 1.913,
      "mktcap": 619684.19392,
      "nmc": 608961.112595,
      "turnoverratio": 18.70225
    },
    {
      "symbol": "sz003036",
      "code": "003036",
      "name": "泰坦股份",
      "trade": "29.700",
      "pricechange": 2.7,
      "changepercent": 10,
      "buy": "29.700",
      "sell": "29.700",
      "settlement": "27.000",
      "open": "26.760",
      "high": "29.700",
      "low": "26.110",
      "volume": 13589302,
      "amount": 387566326,
      "ticktime": "14:57:54",
      "per": 72.439,
      "pb": 4.644,
      "mktcap": 642363.58692,
      "nmc": 642347.10342,
      "turnoverratio": 6.28324
    },
    {
      "symbol": "sh603773",
      "code": "603773",
      "name": "沃格光电",
      "trade": "49.520",
      "pricechange": 4.5,
      "changepercent": 9.996,
      "buy": "49.520",
      "sell": "49.520",
      "settlement": "45.020",
      "open": "44.660",
      "high": "49.520",
      "low": "44.600",
      "volume": 18839099,
      "amount": 887907744,
      "ticktime": "14:58:02",
      "per": -89.129,
      "pb": 9.544,
      "mktcap": 1112895.806616,
      "nmc": 1112509.550616,
      "turnoverratio": 8.38566
    },
    {
      "symbol": "sh603890",
      "code": "603890",
      "name": "春秋电子",
      "trade": "18.710",
      "pricechange": 1.7,
      "changepercent": 9.994,
      "buy": "18.710",
      "sell": "18.710",
      "settlement": "17.010",
      "open": "17.140",
      "high": "18.710",
      "low": "17.140",
      "volume": 67300827,
      "amount": 1235508665,
      "ticktime": "14:58:01",
      "per": 38.979,
      "pb": 2.764,
      "mktcap": 835978.518271,
      "nmc": 835978.518271,
      "turnoverratio": 15.06257
    },
    {
      "symbol": "sh605365",
      "code": "605365",
      "name": "立达信",
      "trade": "23.670",
      "pricechange": 2.15,
      "changepercent": 9.991,
      "buy": "23.670",
      "sell": "23.670",
      "settlement": "21.520",
      "open": "21.600",
      "high": "23.670",
      "low": "21.600",
      "volume": 9049251,
      "amount": 212057732,
      "ticktime": "14:58:01",
      "per": 28.45,
      "pb": 3.187,
      "mktcap": 1188264.477492,
      "nmc": 1188264.477492,
      "turnoverratio": 1.80259
    },
    {
      "symbol": "sh600683",
      "code": "600683",
      "name": "京投发展",
      "trade": "9.910",
      "pricechange": 0.9,
      "changepercent": 9.989,
      "buy": "9.910",
      "sell": "9.910",
      "settlement": "9.010",
      "open": "9.080",
      "high": "9.910",
      "low": "8.910",
      "volume": 29036308,
      "amount": 273348852,
      "ticktime": "14:58:01",
      "per": -5.328,
      "pb": -56.758,
      "mktcap": 734110.598627,
      "nmc": 734110.598627,
      "turnoverratio": 3.91971
    },
    {
      "symbol": "sh603698",
      "code": "603698",
      "name": "航天工程",
      "trade": "39.530",
      "pricechange": 3.59,
      "changepercent": 9.989,
      "buy": "39.530",
      "sell": "39.530",
      "settlement": "35.940",
      "open": "39.500",
      "high": "39.530",
      "low": "38.100",
      "volume": 21029733,
      "amount": 830814729,
      "ticktime": "14:58:02",
      "per": 98.825,
      "pb": 6.101,
      "mktcap": 2118768.47,
      "nmc": 2118768.47,
      "turnoverratio": 3.92353
    },
    {
      "symbol": "sz002824",
      "code": "002824",
      "name": "和胜股份",
      "trade": "29.620",
      "pricechange": 2.69,
      "changepercent": 9.989,
      "buy": "29.620",
      "sell": "29.620",
      "settlement": "26.930",
      "open": "27.220",
      "high": "29.620",
      "low": "26.670",
      "volume": 34154616,
      "amount": 983407207,
      "ticktime": "14:57:54",
      "per": 102.138,
      "pb": 4.096,
      "mktcap": 921711.718156,
      "nmc": 651643.37668,
      "turnoverratio": 15.52475
    },
    {
      "symbol": "sz002891",
      "code": "002891",
      "name": "中宠股份",
      "trade": "41.840",
      "pricechange": 3.8,
      "changepercent": 9.989,
      "buy": "41.840",
      "sell": "41.840",
      "settlement": "38.040",
      "open": "38.040",
      "high": "41.840",
      "low": "38.040",
      "volume": 22786943,
      "amount": 925615936,
      "ticktime": "14:57:54",
      "per": 31.226,
      "pb": 4.624,
      "mktcap": 1337345.446872,
      "nmc": 1337345.446872,
      "turnoverratio": 7.12909
    },
    {
      "symbol": "sz000919",
      "code": "000919",
      "name": "金陵药业",
      "trade": "8.260",
      "pricechange": 0.75,
      "changepercent": 9.987,
      "buy": "8.260",
      "sell": "8.260",
      "settlement": "7.510",
      "open": "7.880",
      "high": "8.260",
      "low": "7.710",
      "volume": 74296811,
      "amount": 591133060,
      "ticktime": "14:58:03",
      "per": 95.271,
      "pb": 1.36,
      "mktcap": 513709.660128,
      "nmc": 513579.317328,
      "turnoverratio": 11.94931
    },
    {
      "symbol": "sz002051",
      "code": "002051",
      "name": "中工国际",
      "trade": "11.900",
      "pricechange": 1.08,
      "changepercent": 9.982,
      "buy": "11.900",
      "sell": "11.900",
      "settlement": "10.820",
      "open": "11.390",
      "high": "11.900",
      "low": "11.390",
      "volume": 121174056,
      "amount": 1429200921,
      "ticktime": "14:58:03",
      "per": 41.034,
      "pb": 1.272,
      "mktcap": 1472516.63503,
      "nmc": 1472431.88323,
      "turnoverratio": 9.79313
    },
    {
      "symbol": "sz000889",
      "code": "000889",
      "name": "中嘉博创",
      "trade": "4.740",
      "pricechange": 0.43,
      "changepercent": 9.977,
      "buy": "4.740",
      "sell": "4.740",
      "settlement": "4.310",
      "open": "4.320",
      "high": "4.740",
      "low": "4.030",
      "volume": 317699531,
      "amount": 1398945984,
      "ticktime": "14:58:03",
      "per": -125.397,
      "pb": 62.533,
      "mktcap": 443801.988984,
      "nmc": 412308.746424,
      "turnoverratio": 36.5235
    },
    {
      "symbol": "sh600488",
      "code": "600488",
      "name": "津药药业",
      "trade": "6.840",
      "pricechange": 0.62,
      "changepercent": 9.968,
      "buy": "6.840",
      "sell": "6.840",
      "settlement": "6.220",
      "open": "6.180",
      "high": "6.840",
      "low": "5.960",
      "volume": 241154323,
      "amount": 1560043142,
      "ticktime": "14:58:02",
      "per": 56.066,
      "pb": 2.471,
      "mktcap": 746850.48912,
      "nmc": 746850.48912,
      "turnoverratio": 22.08602
    },
    {
      "symbol": "sz002498",
      "code": "002498",
      "name": "汉缆股份",
      "trade": "8.500",
      "pricechange": 0.77,
      "changepercent": 9.961,
      "buy": "8.500",
      "sell": "8.500",
      "settlement": "7.730",
      "open": "7.780",
      "high": "8.500",
      "low": "7.740",
      "volume": 173071952,
      "amount": 1446586130,
      "ticktime": "14:58:03",
      "per": 43.169,
      "pb": 3.289,
      "mktcap": 2827776.6,
      "nmc": 2827776.6,
      "turnoverratio": 5.20236
    },
    {
      "symbol": "sz002033",
      "code": "002033",
      "name": "丽江股份",
      "trade": "9.940",
      "pricechange": 0.9,
      "changepercent": 9.956,
      "buy": "9.940",
      "sell": "9.940",
      "settlement": "9.040",
      "open": "9.360",
      "high": "9.940",
      "low": "9.310",
      "volume": 72704133,
      "amount": 702513259,
      "ticktime": "14:58:03",
      "per": 25.586,
      "pb": 2.134,
      "mktcap": 546193.766734,
      "nmc": 546183.299914,
      "turnoverratio": 13.23144
    },
    {
      "symbol": "sz002038",
      "code": "002038",
      "name": "双鹭药业",
      "trade": "8.070",
      "pricechange": 0.73,
      "changepercent": 9.946,
      "buy": "8.070",
      "sell": "8.070",
      "settlement": "7.340",
      "open": "7.500",
      "high": "8.070",
      "low": "7.230",
      "volume": 142109840,
      "amount": 1088834864,
      "ticktime": "14:58:03",
      "per": -115.286,
      "pb": 1.456,
      "mktcap": 829071.45,
      "nmc": 687494.169483,
      "turnoverratio": 16.68125
    },
    {
      "symbol": "sh600594",
      "code": "600594",
      "name": "益佰制药",
      "trade": "4.760",
      "pricechange": 0.43,
      "changepercent": 9.931,
      "buy": "4.760",
      "sell": "4.760",
      "settlement": "4.330",
      "open": "4.400",
      "high": "4.760",
      "low": "4.220",
      "volume": 185264087,
      "amount": 845891272,
      "ticktime": "14:58:00",
      "per": -11.841,
      "pb": 1.569,
      "mktcap": 376957.4424,
      "nmc": 376957.4424,
      "turnoverratio": 23.39407
    },
    {
      "symbol": "sh600664",
      "code": "600664",
      "name": "哈药股份",
      "trade": "4.440",
      "pricechange": 0.4,
      "changepercent": 9.901,
      "buy": "4.440",
      "sell": "4.440",
      "settlement": "4.040",
      "open": "4.280",
      "high": "4.440",
      "low": "4.010",
      "volume": 457080064,
      "amount": 1972581059,
      "ticktime": "14:58:00",
      "per": 17.76,
      "pb": 1.976,
      "mktcap": 1118218.384944,
      "nmc": 1118218.384944,
      "turnoverratio": 18.14883
    }
  ],
  "limit_down": [
    {
      "symbol": "sz301292",
      "code": "301292",
      "name": "海科新源",
      "trade": "93.270",
      "pricechange": -13.59,
      "changepercent": -12.718,
      "buy": "93.210",
      "sell": "93.210",
      "settlement": "106.860",
      "open": "102.000",
      "high": "103.400",
      "low": "92.860",
      "volume": 30952248,
      "amount": 2995921886,
      "ticktime": "14:57:54",
      "per": -77.725,
      "pb": 7.676,
      "mktcap": 2078016.221406,
      "nmc": 793435.270569,
      "turnoverratio": 36.38502
    },
    {
      "symbol": "sz002634",
      "code": "002634",
      "name": "棒杰股份",
      "trade": "6.710",
      "pricechange": -0.75,
      "changepercent": -10.054,
      "buy": "6.710",
      "sell": "6.710",
      "settlement": "7.460",
      "open": "6.710",
      "high": "6.710",
      "low": "6.710",
      "volume": 4740200,
      "amount": 31806742,
      "ticktime": "14:58:03",
      "per": -4.534,
      "pb": -5.075,
      "mktcap": 308225.536223,
      "nmc": 299611.254998,
      "turnoverratio": 1.0616
    },
    {
      "symbol": "sz000838",
      "code": "000838",
      "name": "财信发展",
      "trade": "1.880",
      "pricechange": -0.21,
      "changepercent": -10.048,
      "buy": "1.880",
      "sell": "1.880",
      "settlement": "2.090",
      "open": "2.120",
      "high": "2.120",
      "low": "1.880",
      "volume": 90658983,
      "amount": 174636316,
      "ticktime": "14:58:03",
      "per": -7.953,
      "pb": 5.043,
      "mktcap": 206886.88796,
      "nmc": 198107.98074,
      "turnoverratio": 8.60333
    },
    {
      "symbol": "sh603778",
      "code": "603778",
      "name": "国晟科技",
      "trade": "26.810",
      "pricechange": -2.98,
      "changepercent": -10.003,
      "buy": "26.810",
      "sell": "26.810",
      "settlement": "29.790",
      "open": "26.810",
      "high": "26.810",
      "low": "26.810",
      "volume": 4530000,
      "amount": 121449300,
      "ticktime": "14:58:02",
      "per": -167.563,
      "pb": 24.324,
      "mktcap": 1769572.92372,
      "nmc": 1723499.997702,
      "turnoverratio": 0.70467
    },
    {
      "symbol": "sz002227",
      "code": "002227",
      "name": "奥 特 迅",
      "trade": "8.020",
      "pricechange": -0.89,
      "changepercent": -9.989,
      "buy": "8.020",
      "sell": "8.020",
      "settlement": "8.910",
      "open": "8.770",
      "high": "8.790",
      "low": "8.020",
      "volume": 14763356,
      "amount": 122732142,
      "ticktime": "14:58:03",
      "per": -37.6,
      "pb": 2.082,
      "mktcap": 198740.54834,
      "nmc": 197241.286332,
      "turnoverratio": 6.00291
    },
    {
      "symbol": "sh605167",
      "code": "605167",
      "name": "利柏特",
      "trade": "17.680",
      "pricechange": -1.96,
      "changepercent": -9.98,
      "buy": "17.730",
      "sell": "17.730",
      "settlement": "19.640",
      "open": "19.640",
      "high": "20.150",
      "low": "17.680",
      "volume": 20904842,
      "amount": 386733188,
      "ticktime": "14:58:00",
      "per": 32.145,
      "pb": 4.018,
      "mktcap": 794007.569472,
      "nmc": 794007.569472,
      "turnoverratio": 4.65484
    },
    {
      "symbol": "sz002083",
      "code": "002083",
      "name": "孚日股份",
      "trade": "13.080",
      "pricechange": -1.45,
      "changepercent": -9.979,
      "buy": "13.080",
      "sell": "13.080",
      "settlement": "14.530",
      "open": "13.500",
      "high": "13.750",
      "low": "13.080",
      "volume": 126098590,
      "amount": 1679072186,
      "ticktime": "14:58:03",
      "per": 27.83,
      "pb": 2.535,
      "mktcap": 1238203.827696,
      "nmc": 1238203.827696,
      "turnoverratio": 13.32066
    },
    {
      "symbol": "sz001299",
      "code": "001299",
      "name": "美能能源",
      "trade": "16.690",
      "pricechange": -1.85,
      "changepercent": -9.978,
      "buy": "16.690",
      "sell": "16.690",
      "settlement": "18.540",
      "open": "18.360",
      "high": "19.100",
      "low": "16.690",
      "volume": 38082451,
      "amount": 666271293,
      "ticktime": "14:58:03",
      "per": 38.814,
      "pb": 3.337,
      "mktcap": 404963.833414,
      "nmc": 364509.464811,
      "turnoverratio": 17.43703
    },
    {
      "symbol": "sh600743",
      "code": "600743",
      "name": "华远控股",
      "trade": "2.890",
      "pricechange": -0.32,
      "changepercent": -9.969,
      "buy": "2.890",
      "sell": "2.890",
      "settlement": "3.210",
      "open": "3.530",
      "high": "3.530",
      "low": "2.890",
      "volume": 449083701,
      "amount": 1400927808,
      "ticktime": "14:58:01",
      "per": -4.231,
      "pb": 10.712,
      "mktcap": 678023.152586,
      "nmc": 678023.152586,
      "turnoverratio": 19.1417
    },
    {
      "symbol": "sz002575",
      "code": "002575",
      "name": "群兴玩具",
      "trade": "6.510",
      "pricechange": -0.72,
      "changepercent": -9.959,
      "buy": "6.510",
      "sell": "6.510",
      "settlement": "7.230",
      "open": "7.050",
      "high": "7.170",
      "low": "6.510",
      "volume": 104988535,
      "amount": 699737604,
      "ticktime": "14:58:03",
      "per": -217,
      "pb": 4.841,
      "mktcap": 401341.5,
      "nmc": 381157.5705,
      "turnoverratio": 17.93157
    }
  ],
  "my_stocks": [],
  "source": "efinance+sina"
}