{
  "updated_at": "2026-04-02 13:48",
  "indices": {
    "sh000001": {
      "name": "上证指数",
      "price": "3940.80",
      "pct": "-0.20",
      "high": "3952.58",
      "low": "3912.36"
    },
    "sz399001": {
      "name": "深证成指",
      "price": "13658.25",
      "pct": "-0.35",
      "high": "13680.63",
      "low": "13470.61"
    },
    "sz399006": {
      "name": "创业板指",
      "price": "3229.60",
      "pct": "-0.55",
      "high": "3229.68",
      "low": "3165.27"
    },
    "sh000300": {
      "name": "沪深300",
      "price": "4514.44",
      "pct": "-0.26",
      "high": "4519.69",
      "low": "4472.19"
    }
  },
  "limit_up": [
    {
      "symbol": "bj920230",
      "code": "920230",
      "name": "欧康医药",
      "trade": "14.610",
      "pricechange": 3.37,
      "changepercent": 29.982,
      "buy": "14.610",
      "sell": "0.000",
      "settlement": "11.240",
      "open": "11.600",
      "high": "14.610",
      "low": "11.240",
      "volume": 8271404,
      "amount": 113901242,
      "ticktime": "13:47:55",
      "per": 48.7,
      "pb": 3.618,
      "mktcap": 147148.260195,
      "nmc": 69028.959828,
      "turnoverratio": 17.50645
    },
    {
      "symbol": "sz300834",
      "code": "300834",
      "name": "星辉环材",
      "trade": "43.490",
      "pricechange": 7.25,
      "changepercent": 20.006,
      "buy": "43.490",
      "sell": "0.000",
      "settlement": "36.240",
      "open": "41.010",
      "high": "43.490",
      "low": "38.800",
      "volume": 22329040,
      "amount": 935869931,
      "ticktime": "13:47:42",
      "per": 85.275,
      "pb": 2.86,
      "mktcap": 842455.023197,
      "nmc": 836864.061871,
      "turnoverratio": 11.60392
    },
    {
      "symbol": "sz300839",
      "code": "300839",
      "name": "博汇股份",
      "trade": "16.690",
      "pricechange": 2.78,
      "changepercent": 19.986,
      "buy": "16.690",
      "sell": "0.000",
      "settlement": "13.910",
      "open": "16.360",
      "high": "16.690",
      "low": "15.570",
      "volume": 21953501,
      "amount": 361818847,
      "ticktime": "13:47:51",
      "per": -13.039,
      "pb": 6.536,
      "mktcap": 492294.206675,
      "nmc": 483491.036133,
      "turnoverratio": 7.5783
    },
    {
      "symbol": "sz301188",
      "code": "301188",
      "name": "力诺药包",
      "trade": "24.050",
      "pricechange": 3.6,
      "changepercent": 17.604,
      "buy": "24.000",
      "sell": "24.050",
      "settlement": "20.450",
      "open": "21.840",
      "high": "24.500",
      "low": "21.840",
      "volume": 53101391,
      "amount": 1240840738,
      "ticktime": "13:47:57",
      "per": 82.931,
      "pb": 4.246,
      "mktcap": 643425.559075,
      "nmc": 643425.559075,
      "turnoverratio": 19.84827
    },
    {
      "symbol": "sz300086",
      "code": "300086",
      "name": "康芝药业",
      "trade": "9.900",
      "pricechange": 1.37,
      "changepercent": 16.061,
      "buy": "9.900",
      "sell": "9.910",
      "settlement": "8.530",
      "open": "8.790",
      "high": "10.090",
      "low": "8.680",
      "volume": 105610859,
      "amount": 985816711,
      "ticktime": "13:47:57",
      "per": -20.899,
      "pb": 4.292,
      "mktcap": 450573.16689,
      "nmc": 436275.69678,
      "turnoverratio": 23.96529
    },
    {
      "symbol": "sz300547",
      "code": "300547",
      "name": "川环科技",
      "trade": "36.460",
      "pricechange": 4.64,
      "changepercent": 14.582,
      "buy": "36.410",
      "sell": "36.440",
      "settlement": "31.820",
      "open": "31.500",
      "high": "36.970",
      "low": "31.380",
      "volume": 25037824,
      "amount": 865793809,
      "ticktime": "13:47:57",
      "per": 39.007,
      "pb": 6.188,
      "mktcap": 790839.910404,
      "nmc": 649803.234662,
      "turnoverratio": 14.04855
    },
    {
      "symbol": "sh688336",
      "code": "688336",
      "name": "三生国健",
      "trade": "91.000",
      "pricechange": 11.31,
      "changepercent": 14.192,
      "buy": "91.000",
      "sell": "91.010",
      "settlement": "79.690",
      "open": "78.650",
      "high": "93.380",
      "low": "76.250",
      "volume": 16457411,
      "amount": 1365489881,
      "ticktime": "13:47:57",
      "per": 19.362,
      "pb": 6.654,
      "mktcap": 5624587.1773,
      "nmc": 5612750.7163,
      "turnoverratio": 2.66825
    },
    {
      "symbol": "bj920047",
      "code": "920047",
      "name": "诺思兰德",
      "trade": "28.410",
      "pricechange": 3.16,
      "changepercent": 12.515,
      "buy": "28.430",
      "sell": "28.460",
      "settlement": "25.250",
      "open": "25.640",
      "high": "29.760",
      "low": "25.240",
      "volume": 11358488,
      "amount": 316957000,
      "ticktime": "13:47:55",
      "per": -167.118,
      "pb": 26.435,
      "mktcap": 779206.678134,
      "nmc": 511682.359107,
      "turnoverratio": 6.30654
    },
    {
      "symbol": "sz300667",
      "code": "300667",
      "name": "必创科技",
      "trade": "17.750",
      "pricechange": 1.89,
      "changepercent": 11.917,
      "buy": "17.750",
      "sell": "17.780",
      "settlement": "15.860",
      "open": "15.800",
      "high": "17.930",
      "low": "15.710",
      "volume": 19188350,
      "amount": 327290717,
      "ticktime": "13:47:57",
      "per": -25.357,
      "pb": 3.206,
      "mktcap": 363228.969225,
      "nmc": 306419.09135,
      "turnoverratio": 11.11527
    },
    {
      "symbol": "sz300632",
      "code": "300632",
      "name": "光莆股份",
      "trade": "15.090",
      "pricechange": 1.6,
      "changepercent": 11.861,
      "buy": "15.080",
      "sell": "15.090",
      "settlement": "13.490",
      "open": "13.470",
      "high": "15.950",
      "low": "13.350",
      "volume": 36234261,
      "amount": 546665375,
      "ticktime": "13:47:57",
      "per": 88.246,
      "pb": 2.576,
      "mktcap": 460519.06458,
      "nmc": 333784.097022,
      "turnoverratio": 16.3811
    },
    {
      "symbol": "bj920088",
      "code": "920088",
      "name": "科力股份",
      "trade": "59.660",
      "pricechange": 6.12,
      "changepercent": 11.431,
      "buy": "59.600",
      "sell": "59.660",
      "settlement": "53.540",
      "open": "55.000",
      "high": "60.920",
      "low": "55.000",
      "volume": 9012204,
      "amount": 519478566,
      "ticktime": "13:47:55",
      "per": 75.11,
      "pb": 7.826,
      "mktcap": 525434.569,
      "nmc": 191314.191924,
      "turnoverratio": 28.10393
    },
    {
      "symbol": "sh688143",
      "code": "688143",
      "name": "长盈通",
      "trade": "61.960",
      "pricechange": 6.08,
      "changepercent": 10.88,
      "buy": "61.900",
      "sell": "61.960",
      "settlement": "55.880",
      "open": "55.510",
      "high": "63.800",
      "low": "55.000",
      "volume": 16167924,
      "amount": 980847362,
      "ticktime": "13:47:57",
      "per": 413.067,
      "pb": 6.574,
      "mktcap": 797925.849192,
      "nmc": 758231.943496,
      "turnoverratio": 13.21185
    },
    {
      "symbol": "sh688090",
      "code": "688090",
      "name": "瑞松科技",
      "trade": "61.890",
      "pricechange": 5.71,
      "changepercent": 10.164,
      "buy": "61.890",
      "sell": "61.900",
      "settlement": "56.180",
      "open": "57.000",
      "high": "63.500",
      "low": "55.950",
      "volume": 9308317,
      "amount": 571522031,
      "ticktime": "13:47:57",
      "per": 515.75,
      "pb": 8.533,
      "mktcap": 757348.326096,
      "nmc": 757348.326096,
      "turnoverratio": 7.60669
    },
    {
      "symbol": "sh600594",
      "code": "600594",
      "name": "益佰制药",
      "trade": "4.800",
      "pricechange": 0.44,
      "changepercent": 10.092,
      "buy": "4.800",
      "sell": "0.000",
      "settlement": "4.360",
      "open": "4.450",
      "high": "4.800",
      "low": "4.320",
      "volume": 156516000,
      "amount": 717202715,
      "ticktime": "13:47:57",
      "per": -11.94,
      "pb": 1.582,
      "mktcap": 380125.152,
      "nmc": 380125.152,
      "turnoverratio": 19.76393
    },
    {
      "symbol": "sh600488",
      "code": "600488",
      "name": "津药药业",
      "trade": "6.340",
      "pricechange": 0.58,
      "changepercent": 10.069,
      "buy": "6.340",
      "sell": "0.000",
      "settlement": "5.760",
      "open": "6.340",
      "high": "6.340",
      "low": "6.340",
      "volume": 14078795,
      "amount": 89259560,
      "ticktime": "13:47:59",
      "per": 51.967,
      "pb": 2.29,
      "mktcap": 692256.15512,
      "nmc": 692256.15512,
      "turnoverratio": 1.2894
    },
    {
      "symbol": "sz000788",
      "code": "000788",
      "name": "北大医药",
      "trade": "7.220",
      "pricechange": 0.66,
      "changepercent": 10.061,
      "buy": "7.220",
      "sell": "0.000",
      "settlement": "6.560",
      "open": "7.150",
      "high": "7.220",
      "low": "6.920",
      "volume": 135801807,
      "amount": 974615064,
      "ticktime": "13:48:00",
      "per": 31.188,
      "pb": 2.665,
      "mktcap": 430302.92085,
      "nmc": 430302.92085,
      "turnoverratio": 22.78602
    },
    {
      "symbol": "sh605162",
      "code": "605162",
      "name": "新中港",
      "trade": "14.050",
      "pricechange": 1.28,
      "changepercent": 10.023,
      "buy": "14.050",
      "sell": "0.000",
      "settlement": "12.770",
      "open": "13.400",
      "high": "14.050",
      "low": "13.400",
      "volume": 45672443,
      "amount": 633642136,
      "ticktime": "13:47:59",
      "per": 37.973,
      "pb": 4.424,
      "mktcap": 562831.755785,
      "nmc": 562831.755785,
      "turnoverratio": 11.40124
    },
    {
      "symbol": "sh603477",
      "code": "603477",
      "name": "巨星农牧",
      "trade": "17.030",
      "pricechange": 1.55,
      "changepercent": 10.013,
      "buy": "17.030",
      "sell": "0.000",
      "settlement": "15.480",
      "open": "15.470",
      "high": "17.030",
      "low": "15.470",
      "volume": 33896028,
      "amount": 559002516,
      "ticktime": "13:47:57",
      "per": 16.709,
      "pb": 2.918,
      "mktcap": 868649.909933,
      "nmc": 868649.909933,
      "turnoverratio": 6.64536
    },
    {
      "symbol": "sh603863",
      "code": "603863",
      "name": "松炀资源",
      "trade": "17.250",
      "pricechange": 1.57,
      "changepercent": 10.013,
      "buy": "17.250",
      "sell": "0.000",
      "settlement": "15.680",
      "open": "15.640",
      "high": "17.250",
      "low": "15.600",
      "volume": 13878820,
      "amount": 233854410,
      "ticktime": "13:47:56",
      "per": -15,
      "pb": 9.695,
      "mktcap": 353021.25,
      "nmc": 353021.25,
      "turnoverratio": 6.78173
    },
    {
      "symbol": "sh603042",
      "code": "603042",
      "name": "华脉科技",
      "trade": "21.760",
      "pricechange": 1.98,
      "changepercent": 10.01,
      "buy": "21.760",
      "sell": "0.000",
      "settlement": "19.780",
      "open": "19.590",
      "high": "21.760",
      "low": "19.480",
      "volume": 25401488,
      "amount": 539068504,
      "ticktime": "13:47:57",
      "per": 239.912,
      "pb": 4.05,
      "mktcap": 349443.49184,
      "nmc": 349443.49184,
      "turnoverratio": 15.81762
    },
    {
      "symbol": "sh600644",
      "code": "600644",
      "name": "乐山电力",
      "trade": "12.640",
      "pricechange": 1.15,
      "changepercent": 10.009,
      "buy": "12.640",
      "sell": "0.000",
      "settlement": "11.490",
      "open": "12.300",
      "high": "12.640",
      "low": "12.200",
      "volume": 91750783,
      "amount": 1148169897,
      "ticktime": "13:47:58",
      "per": 301.671,
      "pb": 3.458,
      "mktcap": 730997.513952,
      "nmc": 730997.513952,
      "turnoverratio": 15.86503
    },
    {
      "symbol": "sh603122",
      "code": "603122",
      "name": "合富中国",
      "trade": "18.690",
      "pricechange": 1.7,
      "changepercent": 10.006,
      "buy": "18.690",
      "sell": "0.000",
      "settlement": "16.990",
      "open": "17.100",
      "high": "18.690",
      "low": "16.830",
      "volume": 67629940,
      "amount": 1202356789,
      "ticktime": "13:47:56",
      "per": -233.625,
      "pb": 7.032,
      "mktcap": 743960.371077,
      "nmc": 743960.371077,
      "turnoverratio": 16.9902
    },
    {
      "symbol": "sh603353",
      "code": "603353",
      "name": "和顺石油",
      "trade": "36.500",
      "pricechange": 3.32,
      "changepercent": 10.006,
      "buy": "36.500",
      "sell": "0.000",
      "settlement": "33.180",
      "open": "33.780",
      "high": "36.500",
      "low": "33.780",
      "volume": 6189340,
      "amount": 224134693,
      "ticktime": "13:47:52",
      "per": 214.706,
      "pb": 3.804,
      "mktcap": 627456.9,
      "nmc": 622025.7,
      "turnoverratio": 3.63186
    },
    {
      "symbol": "sz000586",
      "code": "000586",
      "name": "汇源通信",
      "trade": "17.150",
      "pricechange": 1.56,
      "changepercent": 10.006,
      "buy": "17.150",
      "sell": "0.000",
      "settlement": "15.590",
      "open": "15.590",
      "high": "17.150",
      "low": "15.590",
      "volume": 12391025,
      "amount": 209321531,
      "ticktime": "13:47:54",
      "per": -355.072,
      "pb": 9.797,
      "mktcap": 331749.6,
      "nmc": 331749.6,
      "turnoverratio": 6.40562
    },
    {
      "symbol": "sh603798",
      "code": "603798",
      "name": "康普顿",
      "trade": "15.620",
      "pricechange": 1.42,
      "changepercent": 10,
      "buy": "15.620",
      "sell": "0.000",
      "settlement": "14.200",
      "open": "14.390",
      "high": "15.620",
      "low": "14.170",
      "volume": 10829120,
      "amount": 166103404,
      "ticktime": "13:47:55",
      "per": 74.381,
      "pb": 3.466,
      "mktcap": 400574.3533,
      "nmc": 400574.3533,
      "turnoverratio": 4.22271
    },
    {
      "symbol": "sz000950",
      "code": "000950",
      "name": "重药控股",
      "trade": "6.490",
      "pricechange": 0.59,
      "changepercent": 10,
      "buy": "6.490",
      "sell": "0.000",
      "settlement": "5.900",
      "open": "6.490",
      "high": "6.490",
      "low": "6.490",
      "volume": 71678190,
      "amount": 465191453,
      "ticktime": "13:48:00",
      "per": 40.563,
      "pb": 0.971,
      "mktcap": 1121591.867704,
      "nmc": 1121591.867704,
      "turnoverratio": 4.1476
    },
    {
      "symbol": "sz000762",
      "code": "000762",
      "name": "西藏矿业",
      "trade": "31.260",
      "pricechange": 2.84,
      "changepercent": 9.993,
      "buy": "31.260",
      "sell": "0.000",
      "settlement": "28.420",
      "open": "28.310",
      "high": "31.260",
      "low": "27.880",
      "volume": 61227689,
      "amount": 1874168725,
      "ticktime": "13:48:00",
      "per": 148.857,
      "pb": 5.529,
      "mktcap": 1628080.94424,
      "nmc": 1628022.731868,
      "turnoverratio": 11.75645
    },
    {
      "symbol": "sz002051",
      "code": "002051",
      "name": "中工国际",
      "trade": "9.910",
      "pricechange": 0.9,
      "changepercent": 9.989,
      "buy": "9.910",
      "sell": "0.000",
      "settlement": "9.010",
      "open": "9.000",
      "high": "9.910",
      "low": "8.970",
      "volume": 87205441,
      "amount": 832380133,
      "ticktime": "13:47:57",
      "per": 34.172,
      "pb": 1.06,
      "mktcap": 1226272.256567,
      "nmc": 1226201.677547,
      "turnoverratio": 7.04783
    },
    {
      "symbol": "sz000155",
      "code": "000155",
      "name": "川能动力",
      "trade": "16.970",
      "pricechange": 1.54,
      "changepercent": 9.981,
      "buy": "16.970",
      "sell": "0.000",
      "settlement": "15.430",
      "open": "15.670",
      "high": "16.970",
      "low": "15.280",
      "volume": 85726630,
      "amount": 1396443089,
      "ticktime": "13:48:00",
      "per": 40.405,
      "pb": 3.037,
      "mktcap": 3132947.676374,
      "nmc": 3132947.676374,
      "turnoverratio": 4.64349
    },
    {
      "symbol": "sz000720",
      "code": "000720",
      "name": "新能泰山",
      "trade": "5.400",
      "pricechange": 0.49,
      "changepercent": 9.98,
      "buy": "5.400",
      "sell": "0.000",
      "settlement": "4.910",
      "open": "4.870",
      "high": "5.400",
      "low": "4.660",
      "volume": 243115796,
      "amount": 1290895127,
      "ticktime": "13:47:57",
      "per": -51.282,
      "pb": 2.878,
      "mktcap": 678527.04834,
      "nmc": 678527.04834,
      "turnoverratio": 19.34816
    },
    {
      "symbol": "sz000968",
      "code": "000968",
      "name": "蓝焰控股",
      "trade": "10.910",
      "pricechange": 0.99,
      "changepercent": 9.98,
      "buy": "10.910",
      "sell": "0.000",
      "settlement": "9.920",
      "open": "10.050",
      "high": "10.910",
      "low": "10.050",
      "volume": 36884704,
      "amount": 392038060,
      "ticktime": "13:47:57",
      "per": 24.244,
      "pb": 1.708,
      "mktcap": 1055545.40206,
      "nmc": 1055545.40206,
      "turnoverratio": 3.81236
    },
    {
      "symbol": "sz002828",
      "code": "002828",
      "name": "贝肯能源",
      "trade": "13.790",
      "pricechange": 1.25,
      "changepercent": 9.968,
      "buy": "13.790",
      "sell": "0.000",
      "settlement": "12.540",
      "open": "13.290",
      "high": "13.790",
      "low": "13.010",
      "volume": 27170770,
      "amount": 369488586,
      "ticktime": "13:47:57",
      "per": 689.5,
      "pb": 3.984,
      "mktcap": 277161.9004,
      "nmc": 266921.963525,
      "turnoverratio": 14.03725
    },
    {
      "symbol": "sh603222",
      "code": "603222",
      "name": "济民健康",
      "trade": "10.150",
      "pricechange": 0.92,
      "changepercent": 9.967,
      "buy": "10.150",
      "sell": "0.000",
      "settlement": "9.230",
      "open": "9.210",
      "high": "10.150",
      "low": "9.060",
      "volume": 40756419,
      "amount": 391021108,
      "ticktime": "13:47:56",
      "per": -92.273,
      "pb": 3.81,
      "mktcap": 532966.974225,
      "nmc": 532966.974225,
      "turnoverratio": 7.76179
    },
    {
      "symbol": "bj920367",
      "code": "920367",
      "name": "新赣江",
      "trade": "21.220",
      "pricechange": 1.92,
      "changepercent": 9.948,
      "buy": "21.210",
      "sell": "21.220",
      "settlement": "19.300",
      "open": "19.330",
      "high": "21.790",
      "low": "18.800",
      "volume": 5123676,
      "amount": 105865241,
      "ticktime": "13:47:55",
      "per": 66.313,
      "pb": 3.164,
      "mktcap": 150367.5725,
      "nmc": 89108.250516,
      "turnoverratio": 12.20138
    },
    {
      "symbol": "sz002560",
      "code": "002560",
      "name": "通达股份",
      "trade": "13.050",
      "pricechange": 1.18,
      "changepercent": 9.941,
      "buy": "13.050",
      "sell": "13.060",
      "settlement": "11.870",
      "open": "12.990",
      "high": "13.060",
      "low": "11.930",
      "volume": 205244170,
      "amount": 2634275769,
      "ticktime": "13:47:57",
      "per": 42.097,
      "pb": 2.522,
      "mktcap": 686088.83385,
      "nmc": 591081.48261,
      "turnoverratio": 45.31417
    },
    {
      "symbol": "sz002309",
      "code": "002309",
      "name": "中利集团",
      "trade": "4.980",
      "pricechange": 0.45,
      "changepercent": 9.934,
      "buy": "4.980",
      "sell": "0.000",
      "settlement": "4.530",
      "open": "4.550",
      "high": "4.980",
      "low": "4.550",
      "volume": 712233595,
      "amount": 3515398343,
      "ticktime": "13:47:57",
      "per": -10.826,
      "pb": 8.049,
      "mktcap": 1497817.36173,
      "nmc": 1198253.889384,
      "turnoverratio": 29.60077
    }
  ],
  "limit_down": [
    {
      "symbol": "sz301338",
      "code": "301338",
      "name": "凯格精机",
      "trade": "159.920",
      "pricechange": -20.25,
      "changepercent": -11.239,
      "buy": "159.800",
      "sell": "159.990",
      "settlement": "180.170",
      "open": "176.060",
      "high": "180.000",
      "low": "158.000",
      "volume": 5949007,
      "amount": 988533934,
      "ticktime": "13:48:06",
      "per": 242.303,
      "pb": 10.867,
      "mktcap": 1701548.8,
      "nmc": 945926.8,
      "turnoverratio": 10.05749
    },
    {
      "symbol": "sh688519",
      "code": "688519",
      "name": "南亚新材",
      "trade": "118.620",
      "pricechange": -14.92,
      "changepercent": -11.173,
      "buy": "118.620",
      "sell": "118.880",
      "settlement": "133.540",
      "open": "130.000",
      "high": "130.000",
      "low": "118.580",
      "volume": 8706827,
      "amount": 1072150754,
      "ticktime": "13:48:07",
      "per": 110.86,
      "pb": 9.679,
      "mktcap": 2784853.625724,
      "nmc": 2784853.625724,
      "turnoverratio": 3.70865
    },
    {
      "symbol": "sh688031",
      "code": "688031",
      "name": "星环科技",
      "trade": "129.690",
      "pricechange": -16.23,
      "changepercent": -11.123,
      "buy": "129.570",
      "sell": "129.760",
      "settlement": "145.920",
      "open": "141.000",
      "high": "142.710",
      "low": "129.000",
      "volume": 8826391,
      "amount": 1185521384,
      "ticktime": "13:48:06",
      "per": -63.887,
      "pb": 18.214,
      "mktcap": 1571011.694604,
      "nmc": 1571011.694604,
      "turnoverratio": 7.28635
    },
    {
      "symbol": "sz002357",
      "code": "002357",
      "name": "富临运业",
      "trade": "13.010",
      "pricechange": -1.45,
      "changepercent": -10.028,
      "buy": "0.000",
      "sell": "13.010",
      "settlement": "14.460",
      "open": "14.880",
      "high": "14.880",
      "low": "13.010",
      "volume": 30246559,
      "amount": 404256850,
      "ticktime": "13:48:06",
      "per": 33.368,
      "pb": 2.369,
      "mktcap": 407849.235836,
      "nmc": 407834.599586,
      "turnoverratio": 9.64871
    },
    {
      "symbol": "sz000048",
      "code": "000048",
      "name": "京基智农",
      "trade": "19.160",
      "pricechange": -2.13,
      "changepercent": -10.005,
      "buy": "0.000",
      "sell": "19.160",
      "settlement": "21.290",
      "open": "20.000",
      "high": "20.600",
      "low": "19.160",
      "volume": 13324800,
      "amount": 258193641,
      "ticktime": "13:48:03",
      "per": 13.914,
      "pb": 2.405,
      "mktcap": 1016020.791,
      "nmc": 1008504.8978,
      "turnoverratio": 2.5315
    },
    {
      "symbol": "sh603008",
      "code": "603008",
      "name": "喜临门",
      "trade": "13.680",
      "pricechange": -1.52,
      "changepercent": -10,
      "buy": "0.000",
      "sell": "13.680",
      "settlement": "15.200",
      "open": "13.680",
      "high": "13.680",
      "low": "13.680",
      "volume": 16149900,
      "amount": 220930632,
      "ticktime": "13:48:07",
      "per": 16.094,
      "pb": 1.289,
      "mktcap": 503824.05108,
      "nmc": 503824.05108,
      "turnoverratio": 4.38508
    },
    {
      "symbol": "sz002905",
      "code": "002905",
      "name": "金逸影视",
      "trade": "10.200",
      "pricechange": -1.13,
      "changepercent": -9.974,
      "buy": "0.000",
      "sell": "10.200",
      "settlement": "11.330",
      "open": "11.000",
      "high": "11.050",
      "low": "10.200",
      "volume": 18938100,
      "amount": 195327023,
      "ticktime": "13:48:00",
      "per": -42.5,
      "pb": 40.412,
      "mktcap": 383846.4,
      "nmc": 356428.8,
      "turnoverratio": 5.41956
    },
    {
      "symbol": "sh600885",
      "code": "600885",
      "name": "宏发股份",
      "trade": "25.360",
      "pricechange": -2.79,
      "changepercent": -9.911,
      "buy": "25.350",
      "sell": "25.360",
      "settlement": "28.150",
      "open": "26.950",
      "high": "27.100",
      "low": "25.340",
      "volume": 58485682,
      "amount": 1503851995,
      "ticktime": "13:48:05",
      "per": 21.133,
      "pb": 3.107,
      "mktcap": 3924699.177768,
      "nmc": 3924699.177768,
      "turnoverratio": 3.77914
    },
    {
      "symbol": "sz002102",
      "code": "002102",
      "name": "能特科技",
      "trade": "3.000",
      "pricechange": -0.33,
      "changepercent": -9.91,
      "buy": "0.000",
      "sell": "3.000",
      "settlement": "3.330",
      "open": "3.100",
      "high": "3.190",
      "low": "3.000",
      "volume": 163838706,
      "amount": 499701761,
      "ticktime": "13:48:06",
      "per": -13.435,
      "pb": 2.241,
      "mktcap": 742688.037,
      "nmc": 651868.5702,
      "turnoverratio": 7.54011
    }
  ],
  "my_stocks": [
    {
      "code": "300548",
      "name": "长芯博创",
      "price": "157.6",
      "pct": "-1.15",
      "high": "163.33",
      "low": "157.12",
      "turnover": "5.87%",
      "pe": "137.23",
      "mktcap": "460亿"
    },
    {
      "code": "688037",
      "name": "芯源微",
      "price": "165.7",
      "pct": "-4.14",
      "high": "171.6",
      "low": "164.78",
      "turnover": "1.4%",
      "pe": "466.01",
      "mktcap": "334亿"
    },
    {
      "code": "603986",
      "name": "兆易创新",
      "price": "246.87",
      "pct": "-3.19",
      "high": "259.8",
      "low": "246.66",
      "turnover": "3.12%",
      "pe": "105.02",
      "mktcap": "1731亿"
    }
  ],
  "source": "efinance+sina"
}