{
  "updated_at": "2026-04-16 09:58",
  "indices": {
    "sh000001": {
      "name": "上证指数",
      "price": "4030.14",
      "pct": "+0.07",
      "high": "4043.69",
      "low": "4028.91"
    },
    "sz399001": {
      "name": "深证成指",
      "price": "14546.35",
      "pct": "+0.33",
      "high": "14662.80",
      "low": "14522.86"
    },
    "sz399006": {
      "name": "创业板指",
      "price": "3531.26",
      "pct": "+0.46",
      "high": "3581.12",
      "low": "3518.36"
    },
    "sh000300": {
      "name": "沪深300",
      "price": "4694.43",
      "pct": "+0.20",
      "high": "4715.29",
      "low": "4689.41"
    }
  },
  "limit_up": [
    {
      "symbol": "sz301666",
      "code": "301666",
      "name": "N大普微",
      "trade": "227.000",
      "pricechange": 180.92,
      "changepercent": 392.622,
      "buy": "226.960",
      "sell": "227.490",
      "settlement": "46.080",
      "open": "207.230",
      "high": "233.230",
      "low": "199.990",
      "volume": 12876382,
      "amount": 2739577001,
      "ticktime": "09:58:06",
      "per": -186.066,
      "pb": 237.746,
      "mktcap": 9902111.372,
      "nmc": 601920.9861,
      "turnoverratio": 48.56017
    },
    {
      "symbol": "sh603293",
      "code": "603293",
      "name": "N埃泰克",
      "trade": "73.440",
      "pricechange": 39.95,
      "changepercent": 119.289,
      "buy": "73.410",
      "sell": "73.440",
      "settlement": "33.490",
      "open": "71.000",
      "high": "85.200",
      "low": "71.000",
      "volume": 11970178,
      "amount": 900083513,
      "ticktime": "09:58:06",
      "per": 0,
      "pb": 8.831,
      "mktcap": 1315241.792352,
      "nmc": 257748.776784,
      "turnoverratio": 34.10646
    },
    {
      "symbol": "bj920177",
      "code": "920177",
      "name": "N恒道",
      "trade": "38.500",
      "pricechange": 16.7,
      "changepercent": 76.606,
      "buy": "38.500",
      "sell": "38.510",
      "settlement": "21.800",
      "open": "40.000",
      "high": "41.010",
      "low": "38.450",
      "volume": 4403241,
      "amount": 175358141,
      "ticktime": "09:58:02",
      "per": 19.059,
      "pb": 3.745,
      "mktcap": 201432,
      "nmc": 45322.2,
      "turnoverratio": 37.40436
    },
    {
      "symbol": "sz300027",
      "code": "300027",
      "name": "华谊兄弟",
      "trade": "2.090",
      "pricechange": 0.35,
      "changepercent": 20.115,
      "buy": "2.090",
      "sell": "0.000",
      "settlement": "1.740",
      "open": "2.090",
      "high": "2.090",
      "low": "2.000",
      "volume": 306477599,
      "amount": 637718868,
      "ticktime": "09:58:06",
      "per": -20.9,
      "pb": 22.023,
      "mktcap": 579871.737071,
      "nmc": 519360.566483,
      "turnoverratio": 12.33321
    },
    {
      "symbol": "sz300905",
      "code": "300905",
      "name": "宝丽迪",
      "trade": "46.320",
      "pricechange": 7.72,
      "changepercent": 20,
      "buy": "46.320",
      "sell": "0.000",
      "settlement": "38.600",
      "open": "41.990",
      "high": "46.320",
      "low": "41.990",
      "volume": 8812212,
      "amount": 397721582,
      "ticktime": "09:58:06",
      "per": 71.262,
      "pb": 4.29,
      "mktcap": 829200.703872,
      "nmc": 646841.341992,
      "turnoverratio": 6.31038
    },
    {
      "symbol": "sz301396",
      "code": "301396",
      "name": "宏景科技",
      "trade": "282.000",
      "pricechange": 40.82,
      "changepercent": 16.925,
      "buy": "281.350",
      "sell": "281.940",
      "settlement": "241.180",
      "open": "248.010",
      "high": "284.440",
      "low": "248.010",
      "volume": 6796919,
      "amount": 1819354288,
      "ticktime": "09:58:06",
      "per": -408.696,
      "pb": 33.585,
      "mktcap": 4329194.8254,
      "nmc": 2145486.2868,
      "turnoverratio": 8.93378
    },
    {
      "symbol": "sz301382",
      "code": "301382",
      "name": "蜂助手",
      "trade": "40.790",
      "pricechange": 5.79,
      "changepercent": 16.543,
      "buy": "40.790",
      "sell": "40.810",
      "settlement": "35.000",
      "open": "36.880",
      "high": "42.000",
      "low": "36.880",
      "volume": 33583763,
      "amount": 1342159687,
      "ticktime": "09:58:06",
      "per": 66.869,
      "pb": 6.289,
      "mktcap": 1164937.530337,
      "nmc": 719080.946502,
      "turnoverratio": 19.05045
    },
    {
      "symbol": "sz301603",
      "code": "301603",
      "name": "乔锋智能",
      "trade": "87.550",
      "pricechange": 12.21,
      "changepercent": 16.207,
      "buy": "87.320",
      "sell": "87.550",
      "settlement": "75.340",
      "open": "79.650",
      "high": "88.000",
      "low": "79.200",
      "volume": 6142683,
      "amount": 512389137,
      "ticktime": "09:58:06",
      "per": 43.995,
      "pb": 4.543,
      "mktcap": 1057253.8,
      "nmc": 330348.0375,
      "turnoverratio": 16.27955
    },
    {
      "symbol": "sh688668",
      "code": "688668",
      "name": "鼎通科技",
      "trade": "199.030",
      "pricechange": 26.34,
      "changepercent": 15.253,
      "buy": "198.770",
      "sell": "199.030",
      "settlement": "172.690",
      "open": "179.000",
      "high": "201.200",
      "low": "176.500",
      "volume": 7943620,
      "amount": 1517136710,
      "ticktime": "09:58:07",
      "per": 115.046,
      "pb": 13.474,
      "mktcap": 2771902.871218,
      "nmc": 2771902.871218,
      "turnoverratio": 5.70373
    },
    {
      "symbol": "sh688287",
      "code": "688287",
      "name": "*ST观典",
      "trade": "2.230",
      "pricechange": 0.27,
      "changepercent": 13.776,
      "buy": "2.220",
      "sell": "2.230",
      "settlement": "1.960",
      "open": "2.200",
      "high": "2.350",
      "low": "2.050",
      "volume": 35658392,
      "amount": 80092252,
      "ticktime": "09:58:05",
      "per": -6.027,
      "pb": 1.078,
      "mktcap": 82624.9788,
      "nmc": 82624.9788,
      "turnoverratio": 9.62399
    },
    {
      "symbol": "sz300390",
      "code": "300390",
      "name": "天华新能",
      "trade": "86.200",
      "pricechange": 9.27,
      "changepercent": 12.05,
      "buy": "86.080",
      "sell": "86.200",
      "settlement": "76.930",
      "open": "78.690",
      "high": "86.280",
      "low": "77.360",
      "volume": 59218076,
      "amount": 4821630598,
      "ticktime": "09:58:06",
      "per": 179.583,
      "pb": 6.308,
      "mktcap": 7161071.79256,
      "nmc": 5794946.54822,
      "turnoverratio": 8.80871
    },
    {
      "symbol": "bj920249",
      "code": "920249",
      "name": "利尔达",
      "trade": "8.820",
      "pricechange": 0.93,
      "changepercent": 11.787,
      "buy": "8.790",
      "sell": "8.800",
      "settlement": "7.890",
      "open": "8.030",
      "high": "9.250",
      "low": "8.030",
      "volume": 9789792,
      "amount": 85055535,
      "ticktime": "09:58:02",
      "per": 88.2,
      "pb": 4.873,
      "mktcap": 371877.66,
      "nmc": 109958.566032,
      "turnoverratio": 7.85259
    },
    {
      "symbol": "sz300088",
      "code": "300088",
      "name": "长信科技",
      "trade": "7.520",
      "pricechange": 0.71,
      "changepercent": 10.426,
      "buy": "7.510",
      "sell": "7.520",
      "settlement": "6.810",
      "open": "6.820",
      "high": "7.750",
      "low": "6.820",
      "volume": 246365166,
      "amount": 1793017691,
      "ticktime": "09:58:06",
      "per": 50.133,
      "pb": 2.149,
      "mktcap": 1878295.651408,
      "nmc": 1869097.802544,
      "turnoverratio": 9.91209
    },
    {
      "symbol": "sz002132",
      "code": "002132",
      "name": "恒星科技",
      "trade": "4.570",
      "pricechange": 0.42,
      "changepercent": 10.12,
      "buy": "4.570",
      "sell": "0.000",
      "settlement": "4.150",
      "open": "4.220",
      "high": "4.570",
      "low": "4.160",
      "volume": 117872790,
      "amount": 519751317,
      "ticktime": "09:58:06",
      "per": 457,
      "pb": 1.845,
      "mktcap": 640505.926986,
      "nmc": 639563.345292,
      "turnoverratio": 8.4226
    },
    {
      "symbol": "sz000782",
      "code": "000782",
      "name": "恒申新材",
      "trade": "5.810",
      "pricechange": 0.53,
      "changepercent": 10.038,
      "buy": "5.810",
      "sell": "0.000",
      "settlement": "5.280",
      "open": "5.320",
      "high": "5.810",
      "low": "5.320",
      "volume": 18188819,
      "amount": 103112741,
      "ticktime": "09:58:06",
      "per": -58.1,
      "pb": 2.32,
      "mktcap": 398903.856729,
      "nmc": 306849.120963,
      "turnoverratio": 3.44394
    },
    {
      "symbol": "sz002726",
      "code": "002726",
      "name": "龙大美食",
      "trade": "3.620",
      "pricechange": 0.33,
      "changepercent": 10.03,
      "buy": "3.620",
      "sell": "0.000",
      "settlement": "3.290",
      "open": "3.620",
      "high": "3.620",
      "low": "3.570",
      "volume": 40840888,
      "amount": 147820740,
      "ticktime": "09:58:06",
      "per": 181,
      "pb": 3.617,
      "mktcap": 390656.169418,
      "nmc": 390359.691418,
      "turnoverratio": 3.78738
    },
    {
      "symbol": "sh600961",
      "code": "600961",
      "name": "株冶集团",
      "trade": "20.080",
      "pricechange": 1.83,
      "changepercent": 10.027,
      "buy": "20.080",
      "sell": "0.000",
      "settlement": "18.250",
      "open": "18.550",
      "high": "20.080",
      "low": "18.550",
      "volume": 22970544,
      "amount": 452908495,
      "ticktime": "09:58:05",
      "per": 30.424,
      "pb": 5.879,
      "mktcap": 2154328.387624,
      "nmc": 1509639.295184,
      "turnoverratio": 3.05536
    },
    {
      "symbol": "sz000967",
      "code": "000967",
      "name": "盈峰环境",
      "trade": "13.070",
      "pricechange": 1.19,
      "changepercent": 10.017,
      "buy": "13.070",
      "sell": "0.000",
      "settlement": "11.880",
      "open": "12.340",
      "high": "13.070",
      "low": "12.150",
      "volume": 125018899,
      "amount": 1593182288,
      "ticktime": "09:58:06",
      "per": 81.688,
      "pb": 2.424,
      "mktcap": 4139196.428825,
      "nmc": 4137210.515517,
      "turnoverratio": 3.94951
    },
    {
      "symbol": "sh603906",
      "code": "603906",
      "name": "龙蟠科技",
      "trade": "25.050",
      "pricechange": 2.28,
      "changepercent": 10.013,
      "buy": "25.050",
      "sell": "0.000",
      "settlement": "22.770",
      "open": "24.100",
      "high": "25.050",
      "low": "24.100",
      "volume": 20571911,
      "amount": 510923971,
      "ticktime": "09:58:08",
      "per": -22.773,
      "pb": 5.736,
      "mktcap": 1716122.652015,
      "nmc": 1415522.652015,
      "turnoverratio": 3.64054
    },
    {
      "symbol": "sz002580",
      "code": "002580",
      "name": "圣阳股份",
      "trade": "27.800",
      "pricechange": 2.53,
      "changepercent": 10.012,
      "buy": "27.800",
      "sell": "0.000",
      "settlement": "25.270",
      "open": "26.570",
      "high": "27.800",
      "low": "26.260",
      "volume": 64503918,
      "amount": 1760303367,
      "ticktime": "09:58:06",
      "per": 61.778,
      "pb": 5.422,
      "mktcap": 1261755.80054,
      "nmc": 1257501.864,
      "turnoverratio": 14.26009
    },
    {
      "symbol": "sz002940",
      "code": "002940",
      "name": "昂利康",
      "trade": "35.600",
      "pricechange": 3.24,
      "changepercent": 10.012,
      "buy": "35.600",
      "sell": "0.000",
      "settlement": "32.360",
      "open": "31.610",
      "high": "35.600",
      "low": "31.430",
      "volume": 17521420,
      "amount": 605121672,
      "ticktime": "09:58:06",
      "per": 89,
      "pb": 4.506,
      "mktcap": 718152.34216,
      "nmc": 659580.66252,
      "turnoverratio": 9.45696
    },
    {
      "symbol": "sz001203",
      "code": "001203",
      "name": "大中矿业",
      "trade": "46.390",
      "pricechange": 4.22,
      "changepercent": 10.007,
      "buy": "46.390",
      "sell": "0.000",
      "settlement": "42.170",
      "open": "43.010",
      "high": "46.390",
      "low": "42.690",
      "volume": 15620171,
      "amount": 704594473,
      "ticktime": "09:58:06",
      "per": 90.961,
      "pb": 11.1,
      "mktcap": 7111960.137965,
      "nmc": 6058413.951958,
      "turnoverratio": 1.19606
    },
    {
      "symbol": "sz000815",
      "code": "000815",
      "name": "美利云",
      "trade": "22.210",
      "pricechange": 2.02,
      "changepercent": 10.005,
      "buy": "22.210",
      "sell": "0.000",
      "settlement": "20.190",
      "open": "20.180",
      "high": "22.210",
      "low": "20.160",
      "volume": 67809807,
      "amount": 1474668543,
      "ticktime": "09:58:06",
      "per": -28.114,
      "pb": 11.435,
      "mktcap": 1544179.200735,
      "nmc": 1544179.200735,
      "turnoverratio": 9.75312
    },
    {
      "symbol": "sz001268",
      "code": "001268",
      "name": "联合精密",
      "trade": "31.340",
      "pricechange": 2.85,
      "changepercent": 10.004,
      "buy": "31.340",
      "sell": "0.000",
      "settlement": "28.490",
      "open": "28.680",
      "high": "31.340",
      "low": "28.640",
      "volume": 2496164,
      "amount": 76693046,
      "ticktime": "09:58:06",
      "per": 47.485,
      "pb": 3.295,
      "mktcap": 338263.068756,
      "nmc": 197233.068756,
      "turnoverratio": 3.96636
    },
    {
      "symbol": "sh603052",
      "code": "603052",
      "name": "可川科技",
      "trade": "75.770",
      "pricechange": 6.89,
      "changepercent": 10.003,
      "buy": "75.770",
      "sell": "0.000",
      "settlement": "68.880",
      "open": "68.800",
      "high": "75.770",
      "low": "68.200",
      "volume": 5856353,
      "amount": 430220911,
      "ticktime": "09:58:04",
      "per": 151.54,
      "pb": 13.087,
      "mktcap": 1423697.705714,
      "nmc": 1423697.705714,
      "turnoverratio": 3.11678
    },
    {
      "symbol": "sh605060",
      "code": "605060",
      "name": "联德股份",
      "trade": "58.950",
      "pricechange": 5.36,
      "changepercent": 10.002,
      "buy": "58.950",
      "sell": "0.000",
      "settlement": "53.590",
      "open": "53.560",
      "high": "58.950",
      "low": "53.560",
      "volume": 7616900,
      "amount": 434976062,
      "ticktime": "09:58:05",
      "per": 62.053,
      "pb": 5.747,
      "mktcap": 1418289.84,
      "nmc": 1408553.658,
      "turnoverratio": 3.18778
    },
    {
      "symbol": "sh603897",
      "code": "603897",
      "name": "长城科技",
      "trade": "50.600",
      "pricechange": 4.6,
      "changepercent": 10,
      "buy": "50.600",
      "sell": "0.000",
      "settlement": "46.000",
      "open": "46.100",
      "high": "50.600",
      "low": "46.100",
      "volume": 10631307,
      "amount": 532421074,
      "ticktime": "09:58:06",
      "per": 44.386,
      "pb": 4.344,
      "mktcap": 1044564.54586,
      "nmc": 1044564.54586,
      "turnoverratio": 5.14994
    },
    {
      "symbol": "sz002263",
      "code": "002263",
      "name": "大东南",
      "trade": "5.170",
      "pricechange": 0.47,
      "changepercent": 10,
      "buy": "5.170",
      "sell": "0.000",
      "settlement": "4.700",
      "open": "4.700",
      "high": "5.170",
      "low": "4.700",
      "volume": 231036096,
      "amount": 1183000583,
      "ticktime": "09:58:06",
      "per": 517,
      "pb": 3.509,
      "mktcap": 971112.1717,
      "nmc": 971104.4167,
      "turnoverratio": 12.29998
    },
    {
      "symbol": "sz002771",
      "code": "002771",
      "name": "真视通",
      "trade": "18.370",
      "pricechange": 1.67,
      "changepercent": 10,
      "buy": "18.370",
      "sell": "0.000",
      "settlement": "16.700",
      "open": "16.900",
      "high": "18.370",
      "low": "16.900",
      "volume": 19139253,
      "amount": 347049006,
      "ticktime": "09:58:06",
      "per": -61.233,
      "pb": 6.365,
      "mktcap": 385336.6517,
      "nmc": 320583.421235,
      "turnoverratio": 10.96713
    },
    {
      "symbol": "sz002850",
      "code": "002850",
      "name": "科达利",
      "trade": "205.590",
      "pricechange": 18.69,
      "changepercent": 10,
      "buy": "205.590",
      "sell": "0.000",
      "settlement": "186.900",
      "open": "194.830",
      "high": "205.590",
      "low": "192.020",
      "volume": 4334920,
      "amount": 864992901,
      "ticktime": "09:58:06",
      "per": 31.874,
      "pb": 4.306,
      "mktcap": 5669145.648012,
      "nmc": 4092860.596902,
      "turnoverratio": 2.17749
    },
    {
      "symbol": "sh603920",
      "code": "603920",
      "name": "世运电路",
      "trade": "58.860",
      "pricechange": 5.35,
      "changepercent": 9.998,
      "buy": "58.860",
      "sell": "0.000",
      "settlement": "53.510",
      "open": "58.860",
      "high": "58.860",
      "low": "58.860",
      "volume": 11243224,
      "amount": 661776165,
      "ticktime": "09:58:06",
      "per": 54,
      "pb": 6.354,
      "mktcap": 4241406.377862,
      "nmc": 4241406.377862,
      "turnoverratio": 1.56028
    },
    {
      "symbol": "sh605287",
      "code": "605287",
      "name": "德才股份",
      "trade": "46.980",
      "pricechange": 4.27,
      "changepercent": 9.998,
      "buy": "46.980",
      "sell": "0.000",
      "settlement": "42.710",
      "open": "43.560",
      "high": "46.980",
      "low": "43.180",
      "volume": 4314340,
      "amount": 196558160,
      "ticktime": "09:58:06",
      "per": -22.696,
      "pb": 4.235,
      "mktcap": 657720,
      "nmc": 657720,
      "turnoverratio": 3.08167
    },
    {
      "symbol": "sz002990",
      "code": "002990",
      "name": "盛视科技",
      "trade": "46.320",
      "pricechange": 4.21,
      "changepercent": 9.998,
      "buy": "46.320",
      "sell": "0.000",
      "settlement": "42.110",
      "open": "42.420",
      "high": "46.320",
      "low": "42.070",
      "volume": 17763280,
      "amount": 794572521,
      "ticktime": "09:58:06",
      "per": 140.364,
      "pb": 4.872,
      "mktcap": 1212899.103216,
      "nmc": 629019.175416,
      "turnoverratio": 13.0806
    },
    {
      "symbol": "sh600683",
      "code": "600683",
      "name": "京投发展",
      "trade": "10.900",
      "pricechange": 0.99,
      "changepercent": 9.99,
      "buy": "10.900",
      "sell": "0.000",
      "settlement": "9.910",
      "open": "10.400",
      "high": "10.900",
      "low": "10.200",
      "volume": 22667628,
      "amount": 243985825,
      "ticktime": "09:58:08",
      "per": -5.86,
      "pb": -62.428,
      "mktcap": 807447.58073,
      "nmc": 807447.58073,
      "turnoverratio": 3.05998
    },
    {
      "symbol": "sz002297",
      "code": "002297",
      "name": "博云新材",
      "trade": "16.080",
      "pricechange": 1.46,
      "changepercent": 9.986,
      "buy": "16.080",
      "sell": "0.000",
      "settlement": "14.620",
      "open": "16.080",
      "high": "16.080",
      "low": "15.930",
      "volume": 123569508,
      "amount": 1986447881,
      "ticktime": "09:58:06",
      "per": 149.027,
      "pb": 4.332,
      "mktcap": 921552.548952,
      "nmc": 921552.548952,
      "turnoverratio": 21.56141
    },
    {
      "symbol": "sh600768",
      "code": "600768",
      "name": "宁波富邦",
      "trade": "17.520",
      "pricechange": 1.59,
      "changepercent": 9.981,
      "buy": "17.520",
      "sell": "0.000",
      "settlement": "15.930",
      "open": "16.700",
      "high": "17.520",
      "low": "16.700",
      "volume": 10007639,
      "amount": 173051600,
      "ticktime": "09:58:08",
      "per": 39.818,
      "pb": 5.453,
      "mktcap": 234325.0944,
      "nmc": 234325.0944,
      "turnoverratio": 7.4825
    },
    {
      "symbol": "sh603687",
      "code": "603687",
      "name": "大胜达",
      "trade": "19.840",
      "pricechange": 1.8,
      "changepercent": 9.978,
      "buy": "19.840",
      "sell": "0.000",
      "settlement": "18.040",
      "open": "19.000",
      "high": "19.840",
      "low": "18.660",
      "volume": 42484312,
      "amount": 827692892,
      "ticktime": "09:58:05",
      "per": 104.421,
      "pb": 3.348,
      "mktcap": 1091263.218176,
      "nmc": 1091263.218176,
      "turnoverratio": 7.72397
    },
    {
      "symbol": "sz300051",
      "code": "300051",
      "name": "琏升科技",
      "trade": "17.650",
      "pricechange": 1.6,
      "changepercent": 9.969,
      "buy": "17.640",
      "sell": "17.650",
      "settlement": "16.050",
      "open": "15.730",
      "high": "18.000",
      "low": "15.730",
      "volume": 29777600,
      "amount": 502112687,
      "ticktime": "09:58:06",
      "per": -58.833,
      "pb": 40.706,
      "mktcap": 656611.22285,
      "nmc": 648948.166475,
      "turnoverratio": 8.09887
    },
    {
      "symbol": "sz000570",
      "code": "000570",
      "name": "苏常柴Ａ",
      "trade": "6.740",
      "pricechange": 0.61,
      "changepercent": 9.951,
      "buy": "6.740",
      "sell": "0.000",
      "settlement": "6.130",
      "open": "6.190",
      "high": "6.740",
      "low": "6.100",
      "volume": 55671159,
      "amount": 359244601,
      "ticktime": "09:58:06",
      "per": 93.611,
      "pb": 1.381,
      "mktcap": 475636.749718,
      "nmc": 374536.749718,
      "turnoverratio": 10.01834
    },
    {
      "symbol": "sz002468",
      "code": "002468",
      "name": "申通快递",
      "trade": "18.020",
      "pricechange": 1.63,
      "changepercent": 9.945,
      "buy": "18.010",
      "sell": "18.020",
      "settlement": "16.390",
      "open": "18.000",
      "high": "18.030",
      "low": "17.200",
      "volume": 96119917,
      "amount": 1725462101,
      "ticktime": "09:58:06",
      "per": 26.116,
      "pb": 2.682,
      "mktcap": 2758505.503132,
      "nmc": 2643894.338732,
      "turnoverratio": 6.55125
    }
  ],
  "limit_down": [
    {
      "symbol": "sz300433",
      "code": "300433",
      "name": "蓝思科技",
      "trade": "25.470",
      "pricechange": -4.12,
      "changepercent": -13.924,
      "buy": "25.460",
      "sell": "25.470",
      "settlement": "29.590",
      "open": "26.990",
      "high": "27.180",
      "low": "24.940",
      "volume": 121011024,
      "amount": 3092928177,
      "ticktime": "09:58:18",
      "per": 32.241,
      "pb": 2.462,
      "mktcap": 13444952.99589,
      "nmc": 12657825.922923,
      "turnoverratio": 2.43498
    },
    {
      "symbol": "sz300777",
      "code": "300777",
      "name": "中简科技",
      "trade": "31.840",
      "pricechange": -4.52,
      "changepercent": -12.431,
      "buy": "31.820",
      "sell": "31.840",
      "settlement": "36.360",
      "open": "32.730",
      "high": "32.980",
      "low": "31.330",
      "volume": 20699581,
      "amount": 660053178,
      "ticktime": "09:58:18",
      "per": 44.222,
      "pb": 3.072,
      "mktcap": 1400028.797808,
      "nmc": 1344877.982384,
      "turnoverratio": 4.90063
    },
    {
      "symbol": "sz002634",
      "code": "002634",
      "name": "棒杰股份",
      "trade": "6.040",
      "pricechange": -0.67,
      "changepercent": -9.985,
      "buy": "0.000",
      "sell": "6.040",
      "settlement": "6.710",
      "open": "6.040",
      "high": "6.500",
      "low": "6.040",
      "volume": 41646522,
      "amount": 252153137,
      "ticktime": "09:58:21",
      "per": -4.081,
      "pb": -4.568,
      "mktcap": 277448.917852,
      "nmc": 269694.780952,
      "turnoverratio": 9.32702
    }
  ],
  "my_stocks": [],
  "source": "efinance+sina"
}